[1,0,0,[["cc.JsonAsset",["_name","json"],1]],[[0,0,1,3]],[[0,"Weapon",{"101":{"id":101,"name":"激光枪","weaponType":6,"bulletNum":90,"chamber":1.2,"scatterRatio":0,"shootDelta":0.15,"singleNum":5,"resPath":"weapon101","hurtRange":0,"isCross":0,"bulletId":47,"showPos":2,"fireAudioId":101,"hitEffectId":0,"fireEffectId":0,"dropId":1001,"sortIndex":3,"hitBack":0,"effectType":0,"warning":0,"unlockWay":[0,0],"hurt":[2,2],"shootSpeed":[1500,1500],"hitAudioId":[],"bulletType":[0,100],"attackRange":[500,1000],"qte":[0,0],"duration":[0]},"102":{"id":102,"name":"UZI","weaponType":2,"bulletNum":20,"chamber":1.2,"scatterRatio":0,"shootDelta":0.15,"singleNum":1,"resPath":"weapon102","hurtRange":0,"isCross":0,"bulletId":2,"showPos":2,"fireAudioId":102,"hitEffectId":105,"fireEffectId":0,"dropId":1002,"sortIndex":23,"hitBack":0,"effectType":3,"warning":0,"unlockWay":[0,0],"hurt":[1,1],"shootSpeed":[1500,2500],"hitAudioId":[],"bulletType":[0,100],"attackRange":[400,1000],"qte":[0,0],"duration":[0]},"103":{"id":103,"name":"超级风管炮","weaponType":1,"bulletNum":30,"chamber":1.2,"scatterRatio":0.3,"shootDelta":0.35,"singleNum":6,"resPath":"weapon103","hurtRange":0,"isCross":0,"bulletId":3,"showPos":2,"fireAudioId":103,"hitEffectId":105,"fireEffectId":0,"dropId":1003,"sortIndex":6,"hitBack":0,"effectType":0,"warning":0,"unlockWay":[0,0],"hurt":[3,3],"shootSpeed":[2800,3500],"hitAudioId":[],"bulletType":[0,100],"attackRange":[350,1000],"qte":[0,0],"duration":[0]},"104":{"id":104,"name":"回旋镖","weaponType":2,"bulletNum":18,"chamber":1,"scatterRatio":0,"shootDelta":0.5,"singleNum":1,"resPath":"weapon104","hurtRange":0,"isCross":1,"bulletId":4,"showPos":0,"fireAudioId":104,"hitEffectId":104,"fireEffectId":0,"dropId":1004,"sortIndex":24,"hitBack":0,"effectType":9,"warning":0,"unlockWay":[0,0],"hurt":[5,7],"shootSpeed":[2000,2000],"hitAudioId":[205],"bulletType":[1,1800],"attackRange":[600,1000],"qte":[0,0],"duration":[0]},"105":{"id":105,"name":"冲锋枪","weaponType":2,"bulletNum":45,"chamber":1.3,"scatterRatio":0,"shootDelta":0.15,"singleNum":1,"resPath":"weapon105","hurtRange":0,"isCross":0,"bulletId":5,"showPos":0,"fireAudioId":105,"hitEffectId":110,"fireEffectId":0,"dropId":1005,"sortIndex":8,"hitBack":0,"effectType":2,"warning":0,"unlockWay":[0,0],"hurt":[3,4],"shootSpeed":[1800,2800],"hitAudioId":[],"bulletType":[0,100],"attackRange":[500,1000],"qte":[0,0],"duration":[0]},"106":{"id":106,"name":"火箭筒","weaponType":2,"bulletNum":45,"chamber":1.1,"scatterRatio":0,"shootDelta":0.1,"singleNum":1,"resPath":"weapon106","hurtRange":0,"isCross":0,"bulletId":1,"showPos":2,"fireAudioId":106,"hitEffectId":107,"fireEffectId":0,"dropId":1006,"sortIndex":25,"hitBack":100,"effectType":0,"warning":0,"unlockWay":[0,0],"hurt":[1,1],"shootSpeed":[200,4000,1],"hitAudioId":[206],"bulletType":[0,100],"attackRange":[500,1000],"qte":[0,0],"duration":[0]},"107":{"id":107,"name":"黄金ak47","weaponType":2,"bulletNum":30,"chamber":1.2,"scatterRatio":0,"shootDelta":0.15,"singleNum":1,"resPath":"weapon107","hurtRange":0,"isCross":0,"bulletId":8,"showPos":0,"fireAudioId":107,"hitEffectId":106,"fireEffectId":0,"dropId":1007,"sortIndex":26,"hitBack":0,"effectType":0,"warning":0,"unlockWay":[0,0],"hurt":[3,4],"shootSpeed":[1500,2800],"hitAudioId":[],"bulletType":[0,100],"attackRange":[450,1000],"qte":[0,0],"duration":[0]},"109":{"id":109,"name":"离子炮","weaponType":2,"bulletNum":10,"chamber":1.8,"scatterRatio":0,"shootDelta":0.8,"singleNum":1,"resPath":"weapon109","hurtRange":200,"isCross":0,"bulletId":9,"showPos":2,"fireAudioId":109,"hitEffectId":109,"fireEffectId":0,"dropId":1009,"sortIndex":12,"hitBack":750,"effectType":1,"warning":0,"unlockWay":[0,0],"hurt":[1,1],"shootSpeed":[500,2000,1],"hitAudioId":[207],"bulletType":[0,100],"attackRange":[500,1000],"qte":[0,0],"duration":[0]},"111":{"id":111,"name":"蓝火加特林","weaponType":1,"bulletNum":90,"chamber":1.2,"scatterRatio":0.4,"shootDelta":0.15,"singleNum":8,"resPath":"weapon111","hurtRange":0,"isCross":0,"bulletId":11,"showPos":2,"fireAudioId":111,"hitEffectId":111,"fireEffectId":0,"dropId":1011,"sortIndex":10,"hitBack":0,"effectType":4,"warning":0,"unlockWay":[0,0],"hurt":[1,1],"shootSpeed":[1500,2500],"hitAudioId":[],"bulletType":[0,100],"attackRange":[500,1000],"qte":[0,0],"duration":[0]},"112":{"id":112,"name":"磁力枪","weaponType":2,"bulletNum":7,"chamber":1.4,"scatterRatio":0,"shootDelta":0.8,"singleNum":1,"resPath":"weapon112","hurtRange":0,"isCross":1,"bulletId":12,"showPos":0,"fireAudioId":112,"hitEffectId":112,"fireEffectId":0,"dropId":1012,"sortIndex":18,"hitBack":0,"effectType":6,"warning":0,"unlockWay":[0,0],"hurt":[12,16],"shootSpeed":[2000,2000],"hitAudioId":[],"bulletType":[0,100],"attackRange":[800,1000],"qte":[0,0],"duration":[0]},"117":{"id":117,"name":"烟火枪","weaponType":2,"bulletNum":31,"chamber":1.5,"scatterRatio":0.2,"shootDelta":0.3,"singleNum":4,"resPath":"weapon117","hurtRange":0,"isCross":0,"bulletId":17,"showPos":2,"fireAudioId":117,"hitEffectId":117,"fireEffectId":0,"dropId":1017,"sortIndex":14,"hitBack":0,"effectType":0,"warning":0,"unlockWay":[0,0],"hurt":[1,1],"shootSpeed":[1500,1500],"hitAudioId":[202,203,204],"bulletType":[0,100],"attackRange":[500,1000],"qte":[0,0],"duration":[0]},"120":{"id":120,"name":"光能枪","weaponType":3,"bulletNum":30,"chamber":1,"scatterRatio":0,"shootDelta":0.2,"singleNum":1,"resPath":"weapon120","hurtRange":65,"isCross":1,"bulletId":20,"showPos":2,"fireAudioId":120,"hitEffectId":0,"fireEffectId":120,"dropId":1020,"sortIndex":16,"hitBack":200,"effectType":5,"warning":0,"unlockWay":[0,0],"hurt":[1,1],"shootSpeed":[3000,3000],"hitAudioId":[208],"bulletType":[0,100],"attackRange":[500,1000],"qte":[0,0],"duration":[0]},"121":{"id":121,"name":"电磁自走炮","weaponType":2,"bulletNum":10,"chamber":1.1,"scatterRatio":5,"shootDelta":0.5,"singleNum":1,"resPath":"weapon121","hurtRange":0,"isCross":1,"bulletId":31,"showPos":2,"fireAudioId":123,"hitEffectId":121,"fireEffectId":0,"dropId":1021,"sortIndex":20,"hitBack":200,"effectType":7,"warning":0,"unlockWay":[0,0],"hurt":[1,1],"shootSpeed":[1500,1500],"hitAudioId":[210],"bulletType":[0,100],"attackRange":[500,1000],"qte":[0,0],"duration":[0]},"122":{"id":122,"name":"黑洞","weaponType":2,"bulletNum":10,"chamber":1.5,"scatterRatio":0.3,"shootDelta":1.3,"singleNum":1,"resPath":"weapon122","hurtRange":0,"isCross":1,"bulletId":32,"showPos":2,"fireAudioId":124,"hitEffectId":0,"fireEffectId":0,"dropId":1022,"sortIndex":22,"hitBack":200,"effectType":8,"warning":0,"unlockWay":[0,1],"hurt":[1,1],"shootSpeed":[1,2000,1],"hitAudioId":[209],"bulletType":[0,100],"attackRange":[500,1000],"qte":[0,0],"duration":[0]},"130":{"id":130,"name":"激光枪","weaponType":6,"bulletNum":45,"chamber":1.2,"scatterRatio":0,"shootDelta":0.15,"singleNum":2,"resPath":"weapon101","hurtRange":0,"isCross":0,"bulletId":47,"showPos":2,"fireAudioId":101,"hitEffectId":0,"fireEffectId":0,"dropId":1001,"sortIndex":3,"hitBack":0,"effectType":0,"warning":0,"unlockWay":[0,0],"hurt":[1,1],"shootSpeed":[1500,1500],"hitAudioId":[],"bulletType":[0,100],"attackRange":[500,1000],"qte":[0,0],"duration":[0]},"131":{"id":131,"name":"激光枪","weaponType":6,"bulletNum":45,"chamber":1.2,"scatterRatio":0,"shootDelta":0.15,"singleNum":2,"resPath":"weapon101","hurtRange":0,"isCross":0,"bulletId":47,"showPos":2,"fireAudioId":101,"hitEffectId":0,"fireEffectId":0,"dropId":1001,"sortIndex":3,"hitBack":0,"effectType":0,"warning":0,"unlockWay":[0,0],"hurt":[1,1],"shootSpeed":[1500,1500],"hitAudioId":[],"bulletType":[0,100],"attackRange":[500,1000],"qte":[0,0],"duration":[0]},"132":{"id":132,"name":"激光枪","weaponType":6,"bulletNum":45,"chamber":1.2,"scatterRatio":0,"shootDelta":0.15,"singleNum":2,"resPath":"weapon101","hurtRange":0,"isCross":0,"bulletId":47,"showPos":2,"fireAudioId":101,"hitEffectId":0,"fireEffectId":0,"dropId":1001,"sortIndex":3,"hitBack":0,"effectType":0,"warning":0,"unlockWay":[0,0],"hurt":[1,1],"shootSpeed":[1500,1500],"hitAudioId":[],"bulletType":[0,100],"attackRange":[500,1000],"qte":[0,0],"duration":[0]},"133":{"id":133,"name":"UZI","weaponType":2,"bulletNum":20,"chamber":1.2,"scatterRatio":0,"shootDelta":0.15,"singleNum":1,"resPath":"weapon102","hurtRange":0,"isCross":0,"bulletId":2,"showPos":2,"fireAudioId":102,"hitEffectId":105,"fireEffectId":0,"dropId":1002,"sortIndex":23,"hitBack":0,"effectType":3,"warning":0,"unlockWay":[0,0],"hurt":[1,1],"shootSpeed":[1500,2500],"hitAudioId":[],"bulletType":[0,100],"attackRange":[400,1000],"qte":[0,0],"duration":[0]},"134":{"id":134,"name":"UZI","weaponType":2,"bulletNum":20,"chamber":1.2,"scatterRatio":0,"shootDelta":0.15,"singleNum":1,"resPath":"weapon102","hurtRange":0,"isCross":0,"bulletId":2,"showPos":2,"fireAudioId":102,"hitEffectId":105,"fireEffectId":0,"dropId":1002,"sortIndex":23,"hitBack":0,"effectType":3,"warning":0,"unlockWay":[0,0],"hurt":[1,1],"shootSpeed":[1700,2700],"hitAudioId":[],"bulletType":[0,100],"attackRange":[400,1000],"qte":[0,0],"duration":[0]},"135":{"id":135,"name":"UZI","weaponType":2,"bulletNum":20,"chamber":1.2,"scatterRatio":0,"shootDelta":0.15,"singleNum":1,"resPath":"weapon102","hurtRange":0,"isCross":0,"bulletId":2,"showPos":2,"fireAudioId":102,"hitEffectId":105,"fireEffectId":0,"dropId":1002,"sortIndex":23,"hitBack":0,"effectType":3,"warning":0,"unlockWay":[0,0],"hurt":[1,1],"shootSpeed":[1900,2900],"hitAudioId":[],"bulletType":[0,100],"attackRange":[400,1000],"qte":[0,0],"duration":[0]},"136":{"id":136,"name":"超级风管炮","weaponType":1,"bulletNum":10,"chamber":1.2,"scatterRatio":0.3,"shootDelta":0.8,"singleNum":6,"resPath":"weapon103","hurtRange":0,"isCross":0,"bulletId":3,"showPos":2,"fireAudioId":103,"hitEffectId":105,"fireEffectId":0,"dropId":1003,"sortIndex":6,"hitBack":0,"effectType":0,"warning":0,"unlockWay":[0,0],"hurt":[1,1],"shootSpeed":[2000,3000],"hitAudioId":[],"bulletType":[0,100],"attackRange":[350,1000],"qte":[0,0],"duration":[0]},"137":{"id":137,"name":"超级风管炮","weaponType":1,"bulletNum":10,"chamber":1.2,"scatterRatio":0.3,"shootDelta":0.8,"singleNum":6,"resPath":"weapon103","hurtRange":0,"isCross":0,"bulletId":3,"showPos":2,"fireAudioId":103,"hitEffectId":105,"fireEffectId":0,"dropId":1003,"sortIndex":6,"hitBack":0,"effectType":0,"warning":0,"unlockWay":[0,0],"hurt":[1,1],"shootSpeed":[2000,3000],"hitAudioId":[],"bulletType":[0,100],"attackRange":[350,1000],"qte":[0,0],"duration":[0]},"138":{"id":138,"name":"超级风管炮","weaponType":1,"bulletNum":10,"chamber":1.2,"scatterRatio":0.3,"shootDelta":0.8,"singleNum":6,"resPath":"weapon103","hurtRange":0,"isCross":0,"bulletId":3,"showPos":2,"fireAudioId":103,"hitEffectId":105,"fireEffectId":0,"dropId":1003,"sortIndex":6,"hitBack":0,"effectType":0,"warning":0,"unlockWay":[0,0],"hurt":[1,1],"shootSpeed":[2000,3000],"hitAudioId":[],"bulletType":[0,100],"attackRange":[350,1000],"qte":[0,0],"duration":[0]},"139":{"id":139,"name":"回旋镖","weaponType":2,"bulletNum":18,"chamber":1,"scatterRatio":0,"shootDelta":0.5,"singleNum":1,"resPath":"weapon104","hurtRange":0,"isCross":1,"bulletId":4,"showPos":2,"fireAudioId":104,"hitEffectId":104,"fireEffectId":0,"dropId":1004,"sortIndex":24,"hitBack":0,"effectType":9,"warning":0,"unlockWay":[0,0],"hurt":[1,1],"shootSpeed":[2000,2000],"hitAudioId":[205],"bulletType":[1,1800],"attackRange":[600,1000],"qte":[0,0],"duration":[0]},"140":{"id":140,"name":"回旋镖","weaponType":2,"bulletNum":18,"chamber":1,"scatterRatio":0,"shootDelta":0.5,"singleNum":1,"resPath":"weapon104","hurtRange":0,"isCross":1,"bulletId":4,"showPos":2,"fireAudioId":104,"hitEffectId":104,"fireEffectId":0,"dropId":1004,"sortIndex":24,"hitBack":0,"effectType":9,"warning":0,"unlockWay":[0,0],"hurt":[1,1],"shootSpeed":[2000,2000],"hitAudioId":[205],"bulletType":[1,1800],"attackRange":[600,1000],"qte":[0,0],"duration":[0]},"141":{"id":141,"name":"回旋镖","weaponType":2,"bulletNum":18,"chamber":1,"scatterRatio":0,"shootDelta":0.5,"singleNum":1,"resPath":"weapon104","hurtRange":0,"isCross":1,"bulletId":4,"showPos":2,"fireAudioId":104,"hitEffectId":104,"fireEffectId":0,"dropId":1004,"sortIndex":24,"hitBack":0,"effectType":9,"warning":0,"unlockWay":[0,0],"hurt":[1,1],"shootSpeed":[500,500],"hitAudioId":[205],"bulletType":[1,1800],"attackRange":[600,1000],"qte":[0,0],"duration":[0]},"142":{"id":142,"name":"冲锋枪","weaponType":2,"bulletNum":45,"chamber":1.3,"scatterRatio":0,"shootDelta":0.15,"singleNum":1,"resPath":"weapon105","hurtRange":0,"isCross":0,"bulletId":5,"showPos":2,"fireAudioId":105,"hitEffectId":110,"fireEffectId":0,"dropId":1005,"sortIndex":8,"hitBack":0,"effectType":2,"warning":0,"unlockWay":[0,0],"hurt":[1,1],"shootSpeed":[1800,2800],"hitAudioId":[],"bulletType":[0,100],"attackRange":[500,1000],"qte":[0,0],"duration":[0]},"143":{"id":143,"name":"冲锋枪","weaponType":2,"bulletNum":45,"chamber":1.3,"scatterRatio":0,"shootDelta":0.15,"singleNum":1,"resPath":"weapon105","hurtRange":0,"isCross":0,"bulletId":5,"showPos":2,"fireAudioId":105,"hitEffectId":110,"fireEffectId":0,"dropId":1005,"sortIndex":8,"hitBack":0,"effectType":2,"warning":0,"unlockWay":[0,0],"hurt":[1,1],"shootSpeed":[1800,2800],"hitAudioId":[],"bulletType":[0,100],"attackRange":[500,1000],"qte":[0,0],"duration":[0]},"144":{"id":144,"name":"冲锋枪","weaponType":2,"bulletNum":45,"chamber":1.3,"scatterRatio":0,"shootDelta":0.15,"singleNum":1,"resPath":"weapon105","hurtRange":0,"isCross":0,"bulletId":5,"showPos":2,"fireAudioId":105,"hitEffectId":110,"fireEffectId":0,"dropId":1005,"sortIndex":8,"hitBack":0,"effectType":2,"warning":0,"unlockWay":[0,0],"hurt":[1,1],"shootSpeed":[1800,2800],"hitAudioId":[],"bulletType":[0,100],"attackRange":[500,1000],"qte":[0,0],"duration":[0]},"145":{"id":145,"name":"火箭筒","weaponType":2,"bulletNum":45,"chamber":1.1,"scatterRatio":0,"shootDelta":0.1,"singleNum":1,"resPath":"weapon106","hurtRange":0,"isCross":0,"bulletId":1,"showPos":2,"fireAudioId":106,"hitEffectId":107,"fireEffectId":0,"dropId":1006,"sortIndex":25,"hitBack":100,"effectType":0,"warning":0,"unlockWay":[0,0],"hurt":[1,1],"shootSpeed":[200,4000,1],"hitAudioId":[206],"bulletType":[0,100],"attackRange":[500,1000],"qte":[0,0],"duration":[0]},"146":{"id":146,"name":"火箭筒","weaponType":2,"bulletNum":45,"chamber":1.1,"scatterRatio":0,"shootDelta":0.1,"singleNum":1,"resPath":"weapon106","hurtRange":0,"isCross":0,"bulletId":1,"showPos":2,"fireAudioId":106,"hitEffectId":107,"fireEffectId":0,"dropId":1006,"sortIndex":25,"hitBack":100,"effectType":0,"warning":0,"unlockWay":[0,0],"hurt":[1,1],"shootSpeed":[200,4000,1],"hitAudioId":[206],"bulletType":[0,100],"attackRange":[500,1000],"qte":[0,0],"duration":[0]},"147":{"id":147,"name":"火箭筒","weaponType":2,"bulletNum":45,"chamber":1.1,"scatterRatio":0,"shootDelta":0.1,"singleNum":1,"resPath":"weapon106","hurtRange":0,"isCross":0,"bulletId":1,"showPos":2,"fireAudioId":106,"hitEffectId":107,"fireEffectId":0,"dropId":1006,"sortIndex":25,"hitBack":100,"effectType":0,"warning":0,"unlockWay":[0,0],"hurt":[1,1],"shootSpeed":[200,4000,1],"hitAudioId":[206],"bulletType":[0,100],"attackRange":[500,1000],"qte":[0,0],"duration":[0]},"148":{"id":148,"name":"黄金ak47","weaponType":2,"bulletNum":30,"chamber":1.2,"scatterRatio":0,"shootDelta":0.15,"singleNum":1,"resPath":"weapon107","hurtRange":0,"isCross":0,"bulletId":8,"showPos":2,"fireAudioId":107,"hitEffectId":106,"fireEffectId":0,"dropId":1007,"sortIndex":26,"hitBack":0,"effectType":0,"warning":0,"unlockWay":[0,0],"hurt":[1,1],"shootSpeed":[1900,2900],"hitAudioId":[],"bulletType":[0,100],"attackRange":[450,1000],"qte":[0,0],"duration":[0]},"149":{"id":149,"name":"黄金ak47","weaponType":2,"bulletNum":30,"chamber":1.2,"scatterRatio":0,"shootDelta":0.15,"singleNum":1,"resPath":"weapon107","hurtRange":0,"isCross":0,"bulletId":8,"showPos":2,"fireAudioId":107,"hitEffectId":106,"fireEffectId":0,"dropId":1007,"sortIndex":26,"hitBack":0,"effectType":0,"warning":0,"unlockWay":[0,0],"hurt":[1,1],"shootSpeed":[1900,3400],"hitAudioId":[],"bulletType":[0,100],"attackRange":[450,1000],"qte":[0,0],"duration":[0]},"150":{"id":150,"name":"黄金ak47","weaponType":2,"bulletNum":30,"chamber":1.2,"scatterRatio":0,"shootDelta":0.15,"singleNum":1,"resPath":"weapon107","hurtRange":0,"isCross":0,"bulletId":8,"showPos":2,"fireAudioId":107,"hitEffectId":106,"fireEffectId":0,"dropId":1007,"sortIndex":26,"hitBack":0,"effectType":0,"warning":0,"unlockWay":[0,0],"hurt":[1,1],"shootSpeed":[2000,4000],"hitAudioId":[],"bulletType":[0,100],"attackRange":[450,1000],"qte":[0,0],"duration":[0]},"151":{"id":151,"name":"离子炮","weaponType":2,"bulletNum":10,"chamber":1.8,"scatterRatio":0,"shootDelta":0.8,"singleNum":1,"resPath":"weapon109","hurtRange":200,"isCross":0,"bulletId":9,"showPos":2,"fireAudioId":109,"hitEffectId":109,"fireEffectId":0,"dropId":1009,"sortIndex":12,"hitBack":750,"effectType":1,"warning":0,"unlockWay":[0,0],"hurt":[1,1],"shootSpeed":[500,2000,1],"hitAudioId":[207],"bulletType":[0,100],"attackRange":[500,1000],"qte":[0,0],"duration":[0]},"152":{"id":152,"name":"离子炮","weaponType":2,"bulletNum":10,"chamber":1.8,"scatterRatio":0,"shootDelta":0.8,"singleNum":1,"resPath":"weapon109","hurtRange":200,"isCross":0,"bulletId":9,"showPos":2,"fireAudioId":109,"hitEffectId":109,"fireEffectId":0,"dropId":1009,"sortIndex":12,"hitBack":750,"effectType":1,"warning":0,"unlockWay":[0,0],"hurt":[1,1],"shootSpeed":[500,2000,1],"hitAudioId":[207],"bulletType":[0,100],"attackRange":[500,1000],"qte":[0,0],"duration":[0]},"153":{"id":153,"name":"离子炮","weaponType":2,"bulletNum":10,"chamber":1.8,"scatterRatio":0,"shootDelta":0.8,"singleNum":1,"resPath":"weapon109","hurtRange":200,"isCross":0,"bulletId":9,"showPos":2,"fireAudioId":109,"hitEffectId":109,"fireEffectId":0,"dropId":1009,"sortIndex":12,"hitBack":750,"effectType":1,"warning":0,"unlockWay":[0,0],"hurt":[1,1],"shootSpeed":[500,2000,1],"hitAudioId":[207],"bulletType":[0,100],"attackRange":[500,1000],"qte":[0,0],"duration":[0]},"154":{"id":154,"name":"蓝火加特林","weaponType":1,"bulletNum":25,"chamber":1.2,"scatterRatio":0.4,"shootDelta":0.18,"singleNum":8,"resPath":"weapon111","hurtRange":0,"isCross":0,"bulletId":11,"showPos":2,"fireAudioId":111,"hitEffectId":111,"fireEffectId":0,"dropId":1011,"sortIndex":10,"hitBack":0,"effectType":4,"warning":0,"unlockWay":[0,0],"hurt":[1,1],"shootSpeed":[1500,2500],"hitAudioId":[],"bulletType":[0,100],"attackRange":[500,1000],"qte":[0,0],"duration":[0]},"155":{"id":155,"name":"蓝火加特林","weaponType":1,"bulletNum":25,"chamber":1.2,"scatterRatio":0.4,"shootDelta":0.18,"singleNum":8,"resPath":"weapon111","hurtRange":0,"isCross":0,"bulletId":11,"showPos":2,"fireAudioId":111,"hitEffectId":111,"fireEffectId":0,"dropId":1011,"sortIndex":10,"hitBack":0,"effectType":4,"warning":0,"unlockWay":[0,0],"hurt":[1,1],"shootSpeed":[1800,2800],"hitAudioId":[],"bulletType":[0,100],"attackRange":[500,1000],"qte":[0,0],"duration":[0]},"156":{"id":156,"name":"蓝火加特林","weaponType":1,"bulletNum":25,"chamber":1.2,"scatterRatio":0.4,"shootDelta":0.18,"singleNum":8,"resPath":"weapon111","hurtRange":0,"isCross":0,"bulletId":11,"showPos":2,"fireAudioId":111,"hitEffectId":111,"fireEffectId":0,"dropId":1011,"sortIndex":10,"hitBack":0,"effectType":4,"warning":0,"unlockWay":[0,0],"hurt":[1,1],"shootSpeed":[2000,3000],"hitAudioId":[],"bulletType":[0,100],"attackRange":[500,1000],"qte":[0,0],"duration":[0]},"157":{"id":157,"name":"磁力枪","weaponType":2,"bulletNum":7,"chamber":1.4,"scatterRatio":0,"shootDelta":0.8,"singleNum":1,"resPath":"weapon112","hurtRange":0,"isCross":1,"bulletId":12,"showPos":2,"fireAudioId":112,"hitEffectId":112,"fireEffectId":0,"dropId":1012,"sortIndex":18,"hitBack":0,"effectType":6,"warning":0,"unlockWay":[0,0],"hurt":[1,1],"shootSpeed":[2200,2200],"hitAudioId":[],"bulletType":[0,100],"attackRange":[800,1000],"qte":[0,0],"duration":[0]},"158":{"id":158,"name":"磁力枪","weaponType":2,"bulletNum":7,"chamber":1.4,"scatterRatio":0,"shootDelta":0.8,"singleNum":1,"resPath":"weapon112","hurtRange":0,"isCross":1,"bulletId":12,"showPos":2,"fireAudioId":112,"hitEffectId":112,"fireEffectId":0,"dropId":1012,"sortIndex":18,"hitBack":0,"effectType":6,"warning":0,"unlockWay":[0,0],"hurt":[1,1],"shootSpeed":[2000,2000],"hitAudioId":[],"bulletType":[0,100],"attackRange":[800,1000],"qte":[0,0],"duration":[0]},"159":{"id":159,"name":"磁力枪","weaponType":2,"bulletNum":7,"chamber":1.4,"scatterRatio":0,"shootDelta":0.8,"singleNum":1,"resPath":"weapon112","hurtRange":0,"isCross":1,"bulletId":12,"showPos":2,"fireAudioId":112,"hitEffectId":112,"fireEffectId":0,"dropId":1012,"sortIndex":18,"hitBack":0,"effectType":6,"warning":0,"unlockWay":[0,0],"hurt":[1,1],"shootSpeed":[2000,2000],"hitAudioId":[],"bulletType":[0,100],"attackRange":[800,1000],"qte":[0,0],"duration":[0]},"160":{"id":160,"name":"烟火枪","weaponType":2,"bulletNum":31,"chamber":1.5,"scatterRatio":0.2,"shootDelta":0.3,"singleNum":4,"resPath":"weapon117","hurtRange":0,"isCross":0,"bulletId":17,"showPos":2,"fireAudioId":117,"hitEffectId":117,"fireEffectId":0,"dropId":1017,"sortIndex":14,"hitBack":0,"effectType":0,"warning":0,"unlockWay":[0,0],"hurt":[1,1],"shootSpeed":[1500,1500],"hitAudioId":[202,203,204],"bulletType":[0,100],"attackRange":[500,1000],"qte":[0,0],"duration":[0]},"161":{"id":161,"name":"烟火枪","weaponType":2,"bulletNum":31,"chamber":1.5,"scatterRatio":0.2,"shootDelta":0.3,"singleNum":4,"resPath":"weapon117","hurtRange":0,"isCross":0,"bulletId":17,"showPos":2,"fireAudioId":117,"hitEffectId":117,"fireEffectId":0,"dropId":1017,"sortIndex":14,"hitBack":0,"effectType":0,"warning":0,"unlockWay":[0,0],"hurt":[1,1],"shootSpeed":[1500,1500],"hitAudioId":[202,203,204],"bulletType":[0,100],"attackRange":[500,1000],"qte":[0,0],"duration":[0]},"162":{"id":162,"name":"烟火枪","weaponType":2,"bulletNum":31,"chamber":1.5,"scatterRatio":0.2,"shootDelta":0.3,"singleNum":4,"resPath":"weapon117","hurtRange":130,"isCross":0,"bulletId":17,"showPos":2,"fireAudioId":117,"hitEffectId":117,"fireEffectId":0,"dropId":1017,"sortIndex":14,"hitBack":0,"effectType":0,"warning":0,"unlockWay":[0,0],"hurt":[1,1],"shootSpeed":[1500,1500],"hitAudioId":[202,203,204],"bulletType":[0,100],"attackRange":[500,1000],"qte":[0,0],"duration":[0]},"163":{"id":163,"name":"光能枪","weaponType":3,"bulletNum":45,"chamber":0.9,"scatterRatio":0,"shootDelta":0.15,"singleNum":1,"resPath":"weapon120","hurtRange":65,"isCross":1,"bulletId":20,"showPos":2,"fireAudioId":120,"hitEffectId":0,"fireEffectId":120,"dropId":1020,"sortIndex":16,"hitBack":200,"effectType":5,"warning":0,"unlockWay":[0,0],"hurt":[1,1],"shootSpeed":[3000,3000],"hitAudioId":[208],"bulletType":[0,100],"attackRange":[500,1000],"qte":[0,0],"duration":[0]},"164":{"id":164,"name":"光能枪","weaponType":3,"bulletNum":60,"chamber":0.8,"scatterRatio":0,"shootDelta":0.1,"singleNum":1,"resPath":"weapon120","hurtRange":65,"isCross":1,"bulletId":20,"showPos":2,"fireAudioId":120,"hitEffectId":0,"fireEffectId":120,"dropId":1020,"sortIndex":16,"hitBack":200,"effectType":5,"warning":0,"unlockWay":[0,0],"hurt":[1,1],"shootSpeed":[3000,3000],"hitAudioId":[208],"bulletType":[0,100],"attackRange":[500,1000],"qte":[0,0],"duration":[0]},"165":{"id":165,"name":"光能枪","weaponType":3,"bulletNum":75,"chamber":0.5,"scatterRatio":0,"shootDelta":0.09,"singleNum":1,"resPath":"weapon120","hurtRange":65,"isCross":1,"bulletId":20,"showPos":2,"fireAudioId":120,"hitEffectId":0,"fireEffectId":120,"dropId":1020,"sortIndex":16,"hitBack":200,"effectType":5,"warning":0,"unlockWay":[0,0],"hurt":[1,1],"shootSpeed":[3000,3000],"hitAudioId":[208],"bulletType":[0,100],"attackRange":[500,1000],"qte":[0,0],"duration":[0]},"166":{"id":166,"name":"电磁自走炮","weaponType":2,"bulletNum":18,"chamber":1,"scatterRatio":5,"shootDelta":0.4,"singleNum":1,"resPath":"weapon121","hurtRange":0,"isCross":1,"bulletId":31,"showPos":2,"fireAudioId":123,"hitEffectId":121,"fireEffectId":0,"dropId":1021,"sortIndex":20,"hitBack":200,"effectType":7,"warning":0,"unlockWay":[0,0],"hurt":[1,1],"shootSpeed":[1500,1500],"hitAudioId":[210],"bulletType":[0,100],"attackRange":[500,1000],"qte":[0,0],"duration":[0]},"167":{"id":167,"name":"电磁自走炮","weaponType":2,"bulletNum":22,"chamber":1,"scatterRatio":5,"shootDelta":0.3,"singleNum":1,"resPath":"weapon121","hurtRange":0,"isCross":1,"bulletId":38,"showPos":2,"fireAudioId":123,"hitEffectId":421,"fireEffectId":0,"dropId":1021,"sortIndex":20,"hitBack":200,"effectType":7,"warning":0,"unlockWay":[0,0],"hurt":[1,1],"shootSpeed":[1500,1500],"hitAudioId":[210],"bulletType":[0,100],"attackRange":[500,1000],"qte":[0,0],"duration":[0]},"168":{"id":168,"name":"电磁自走炮","weaponType":2,"bulletNum":4,"chamber":0.9,"scatterRatio":7,"shootDelta":0.2,"singleNum":1,"resPath":"weapon121","hurtRange":0,"isCross":1,"bulletId":38,"showPos":2,"fireAudioId":123,"hitEffectId":421,"fireEffectId":0,"dropId":1021,"sortIndex":20,"hitBack":200,"effectType":7,"warning":0,"unlockWay":[0,0],"hurt":[1,1],"shootSpeed":[2000,2000],"hitAudioId":[210],"bulletType":[0,100],"attackRange":[500,1000],"qte":[0,0],"duration":[0]},"169":{"id":169,"name":"黑洞","weaponType":2,"bulletNum":10,"chamber":1.3,"scatterRatio":0.3,"shootDelta":1,"singleNum":1,"resPath":"weapon122","hurtRange":0,"isCross":1,"bulletId":32,"showPos":2,"fireAudioId":124,"hitEffectId":0,"fireEffectId":0,"dropId":1022,"sortIndex":22,"hitBack":200,"effectType":8,"warning":0,"unlockWay":[0,1],"hurt":[1,1],"shootSpeed":[1,3000,1],"hitAudioId":[209],"bulletType":[0,100],"attackRange":[500,1000],"qte":[0,0],"duration":[0]},"170":{"id":170,"name":"黑洞","weaponType":2,"bulletNum":10,"chamber":1.3,"scatterRatio":0.3,"shootDelta":1,"singleNum":2,"resPath":"weapon122","hurtRange":0,"isCross":1,"bulletId":32,"showPos":2,"fireAudioId":124,"hitEffectId":0,"fireEffectId":0,"dropId":1022,"sortIndex":22,"hitBack":200,"effectType":8,"warning":0,"unlockWay":[0,1],"hurt":[1,1],"shootSpeed":[1,3000,1],"hitAudioId":[209],"bulletType":[0,100],"attackRange":[500,1000],"qte":[0,0],"duration":[0]},"171":{"id":171,"name":"黑洞","weaponType":2,"bulletNum":10,"chamber":1.3,"scatterRatio":0.1,"shootDelta":1.2,"singleNum":1,"resPath":"weapon122","hurtRange":0,"isCross":1,"bulletId":39,"showPos":2,"fireAudioId":124,"hitEffectId":0,"fireEffectId":0,"dropId":1022,"sortIndex":22,"hitBack":400,"effectType":8,"warning":0,"unlockWay":[0,1],"hurt":[1,1],"shootSpeed":[1,3000,1],"hitAudioId":[209],"bulletType":[0,100],"attackRange":[500,1000],"qte":[0,0],"duration":[0]},"301":{"id":301,"name":"蝙蝠小怪攻击","weaponType":1,"bulletNum":99999999,"chamber":0,"scatterRatio":0,"shootDelta":2.5,"singleNum":1,"resPath":"weapon301","hurtRange":0,"isCross":0,"bulletId":23,"showPos":2,"fireAudioId":0,"hitEffectId":0,"fireEffectId":0,"dropId":1001,"sortIndex":0,"hitBack":0,"effectType":0,"warning":0,"unlockWay":[0,0],"hurt":[50,50],"shootSpeed":[350,350],"hitAudioId":[],"bulletType":[1,360],"attackRange":[1000,1000],"qte":[0,0],"duration":[0]},"303":{"id":303,"name":"跟踪子弹","weaponType":2,"bulletNum":99999999,"chamber":0,"scatterRatio":5,"shootDelta":0.3,"singleNum":1,"resPath":"weapon303","hurtRange":0,"isCross":1,"bulletId":22,"showPos":1,"fireAudioId":0,"hitEffectId":121,"fireEffectId":0,"dropId":3003,"sortIndex":0,"hitBack":100,"effectType":7,"warning":0,"unlockWay":[1,21],"hurt":[500,800],"shootSpeed":[1000,1000],"hitAudioId":[],"bulletType":[0,100],"attackRange":[1000,1000],"qte":[0,0],"duration":[0]},"304":{"id":304,"name":"旋转子弹","weaponType":2,"bulletNum":99999999,"chamber":0,"scatterRatio":0,"shootDelta":0.03,"singleNum":1,"resPath":"weapon304","hurtRange":0,"isCross":0,"bulletId":21,"showPos":1,"fireAudioId":0,"hitEffectId":105,"fireEffectId":0,"dropId":3004,"sortIndex":0,"hitBack":100,"effectType":0,"warning":0,"unlockWay":[0,0],"hurt":[250,400],"shootSpeed":[1000,2000,1],"hitAudioId":[],"bulletType":[3,-360],"attackRange":[1000,1000],"qte":[0,0],"duration":[0]},"305":{"id":305,"name":"3发齐发-树-5","weaponType":2,"bulletNum":999,"chamber":0,"scatterRatio":0.3,"shootDelta":3,"singleNum":4,"resPath":"weapon301","hurtRange":0,"isCross":0,"bulletId":47,"showPos":2,"fireAudioId":0,"hitEffectId":0,"fireEffectId":0,"dropId":1001,"sortIndex":0,"hitBack":0,"effectType":0,"warning":0.8,"unlockWay":[0,0],"hurt":[50,50],"shootSpeed":[600,600],"hitAudioId":[],"bulletType":[0,100],"attackRange":[600,1000],"qte":[0,0],"duration":[0]},"306":{"id":306,"name":"7发散发-树-10","weaponType":1,"bulletNum":999,"chamber":0,"scatterRatio":0.5,"shootDelta":2.5,"singleNum":7,"resPath":"weapon301","hurtRange":0,"isCross":0,"bulletId":47,"showPos":2,"fireAudioId":0,"hitEffectId":0,"fireEffectId":0,"dropId":1001,"sortIndex":0,"hitBack":0,"effectType":0,"warning":0,"unlockWay":[0,0],"hurt":[50,50],"shootSpeed":[400,400],"hitAudioId":[],"bulletType":[0,100],"attackRange":[600,1000],"qte":[0,0],"duration":[0]},"307":{"id":307,"name":"机器人16激光15","weaponType":2,"bulletNum":30,"chamber":3,"scatterRatio":0,"shootDelta":0.15,"singleNum":1,"resPath":"weapon301","hurtRange":0,"isCross":0,"bulletId":47,"showPos":2,"fireAudioId":0,"hitEffectId":0,"fireEffectId":0,"dropId":1001,"sortIndex":0,"hitBack":0,"effectType":0,"warning":0,"unlockWay":[0,0],"hurt":[50,50],"shootSpeed":[400,400],"hitAudioId":[],"bulletType":[3,130],"attackRange":[600,1000],"qte":[0,0],"duration":[0]},"308":{"id":308,"name":"双旋转20","weaponType":2,"bulletNum":30,"chamber":3,"scatterRatio":0,"shootDelta":0.1,"singleNum":1,"resPath":"weapon301","hurtRange":0,"isCross":0,"bulletId":47,"showPos":2,"fireAudioId":0,"hitEffectId":0,"fireEffectId":0,"dropId":1001,"sortIndex":0,"hitBack":0,"effectType":0,"warning":0,"unlockWay":[0,0],"hurt":[50,50],"shootSpeed":[400,400],"hitAudioId":[],"bulletType":[3,120],"attackRange":[600,1000],"qte":[1,309],"duration":[[3,3]]},"309":{"id":309,"name":"双旋转大招20","weaponType":2,"bulletNum":30,"chamber":3,"scatterRatio":0,"shootDelta":0.1,"singleNum":1,"resPath":"weapon301","hurtRange":0,"isCross":0,"bulletId":47,"showPos":2,"fireAudioId":0,"hitEffectId":0,"fireEffectId":0,"dropId":1001,"sortIndex":0,"hitBack":0,"effectType":0,"warning":0,"unlockWay":[0,0],"hurt":[50,50],"shootSpeed":[400,400],"hitAudioId":[],"bulletType":[3,-120],"attackRange":[600,1000],"qte":[0,0],"duration":[0]},"310":{"id":310,"name":"机器人3激光5","weaponType":2,"bulletNum":1,"chamber":2.5,"scatterRatio":0.35,"shootDelta":1.5,"singleNum":4,"resPath":"weapon301","hurtRange":0,"isCross":1,"bulletId":45,"showPos":2,"fireAudioId":0,"hitEffectId":0,"fireEffectId":0,"dropId":1001,"sortIndex":0,"hitBack":0,"effectType":0,"warning":1,"unlockWay":[0,0],"hurt":[50,50],"shootSpeed":[3500,3500],"hitAudioId":[],"bulletType":[0,100],"attackRange":[600,1000],"qte":[0,0],"duration":[0]},"311":{"id":311,"name":"喷火龙两次三连发10","weaponType":2,"bulletNum":3,"chamber":3,"scatterRatio":0.6,"shootDelta":0.8,"singleNum":3,"resPath":"weapon105","hurtRange":0,"isCross":0,"bulletId":40,"showPos":2,"fireAudioId":121,"hitEffectId":110,"fireEffectId":0,"dropId":1005,"sortIndex":0,"hitBack":0,"effectType":2,"warning":0,"unlockWay":[0,0],"hurt":[50,50],"shootSpeed":[400,400],"hitAudioId":[],"bulletType":[0,30],"attackRange":[600,1000],"qte":[0,0],"duration":[0]},"312":{"id":312,"name":"机器人16个激光15","weaponType":2,"bulletNum":99999999,"chamber":0,"scatterRatio":0.4,"shootDelta":2,"singleNum":16,"resPath":"weapon301","hurtRange":0,"isCross":1,"bulletId":45,"showPos":2,"fireAudioId":0,"hitEffectId":0,"fireEffectId":0,"dropId":1001,"sortIndex":0,"hitBack":0,"effectType":0,"warning":0.8,"unlockWay":[0,0],"hurt":[50,50],"shootSpeed":[4000,4000],"hitAudioId":[],"bulletType":[0,100],"attackRange":[600,1000],"qte":[0,0],"duration":[0]},"313":{"id":313,"name":"喷火龙8个方向三连发20","weaponType":2,"bulletNum":3,"chamber":3,"scatterRatio":0.78,"shootDelta":0.2,"singleNum":8,"resPath":"weapon105","hurtRange":0,"isCross":0,"bulletId":40,"showPos":2,"fireAudioId":121,"hitEffectId":110,"fireEffectId":0,"dropId":1005,"sortIndex":0,"hitBack":0,"effectType":2,"warning":0,"unlockWay":[0,0],"hurt":[50,50],"shootSpeed":[500,500],"hitAudioId":[],"bulletType":[0,30],"attackRange":[600,1000],"qte":[0,0],"duration":[0]},"314":{"id":314,"name":"喷火龙火柱25","weaponType":2,"bulletNum":30,"chamber":3,"scatterRatio":0,"shootDelta":0.1,"singleNum":1,"resPath":"weapon111","hurtRange":0,"isCross":0,"bulletId":40,"showPos":2,"fireAudioId":111,"hitEffectId":111,"fireEffectId":0,"dropId":1011,"sortIndex":0,"hitBack":0,"effectType":4,"warning":0,"unlockWay":[0,0],"hurt":[50,50],"shootSpeed":[450,450],"hitAudioId":[],"bulletType":[1,250],"attackRange":[600,1000],"qte":[0,0],"duration":[0]},"315":{"id":315,"name":"三连发激光30","weaponType":2,"bulletNum":3,"chamber":3,"scatterRatio":0,"shootDelta":0.5,"singleNum":1,"resPath":"weapon112","hurtRange":0,"isCross":1,"bulletId":45,"showPos":2,"fireAudioId":112,"hitEffectId":0,"fireEffectId":0,"dropId":1012,"sortIndex":0,"hitBack":0,"effectType":6,"warning":0.7,"unlockWay":[0,0],"hurt":[50,50],"shootSpeed":[4000,4000],"hitAudioId":[],"bulletType":[0,100],"attackRange":[600,1000],"qte":[0,0],"duration":[0]},"316":{"id":316,"name":"蝙蝠5个方向快速子弹5","weaponType":2,"bulletNum":3,"chamber":3,"scatterRatio":0.5,"shootDelta":0.1,"singleNum":5,"resPath":"weapon105","hurtRange":0,"isCross":0,"bulletId":43,"showPos":2,"fireAudioId":121,"hitEffectId":110,"fireEffectId":0,"dropId":1005,"sortIndex":0,"hitBack":0,"effectType":2,"warning":0,"unlockWay":[0,0],"hurt":[50,50],"shootSpeed":[600,600],"hitAudioId":[],"bulletType":[1,100],"attackRange":[600,1000],"qte":[0,0],"duration":[0]},"317":{"id":317,"name":"蝙蝠螺旋子弹10","weaponType":2,"bulletNum":70,"chamber":3,"scatterRatio":0,"shootDelta":0.05,"singleNum":1,"resPath":"weapon301","hurtRange":0,"isCross":0,"bulletId":43,"showPos":2,"fireAudioId":0,"hitEffectId":0,"fireEffectId":0,"dropId":1001,"sortIndex":0,"hitBack":0,"effectType":0,"warning":0,"unlockWay":[0,0],"hurt":[50,50],"shootSpeed":[200,500,1],"hitAudioId":[],"bulletType":[3,-360],"attackRange":[600,1000],"qte":[0,0],"duration":[0]},"318":{"id":318,"name":"蝙蝠泼水子弹-紫色15","weaponType":1,"bulletNum":20,"chamber":3,"scatterRatio":0,"shootDelta":0.05,"singleNum":5,"resPath":"weapon111","hurtRange":0,"isCross":0,"bulletId":43,"showPos":2,"fireAudioId":111,"hitEffectId":111,"fireEffectId":0,"dropId":1011,"sortIndex":0,"hitBack":0,"effectType":4,"warning":0,"unlockWay":[0,0],"hurt":[50,50],"shootSpeed":[450,600],"hitAudioId":[],"bulletType":[1,180],"attackRange":[600,1000],"qte":[0,0],"duration":[0]},"319":{"id":319,"name":"石头散发","weaponType":1,"bulletNum":1,"chamber":3,"scatterRatio":0.5,"shootDelta":0.3,"singleNum":10,"resPath":"weapon301","hurtRange":0,"isCross":0,"bulletId":44,"showPos":2,"fireAudioId":0,"hitEffectId":0,"fireEffectId":0,"dropId":1001,"sortIndex":0,"hitBack":0,"effectType":0,"warning":0,"unlockWay":[0,0],"hurt":[50,50],"shootSpeed":[500,300],"hitAudioId":[],"bulletType":[0,0],"attackRange":[600,1000],"qte":[0,0],"duration":[0]},"320":{"id":320,"name":"石头散发","weaponType":2,"bulletNum":20,"chamber":3,"scatterRatio":2.09,"shootDelta":0.2,"singleNum":3,"resPath":"weapon301","hurtRange":0,"isCross":0,"bulletId":44,"showPos":2,"fireAudioId":0,"hitEffectId":0,"fireEffectId":0,"dropId":1001,"sortIndex":0,"hitBack":0,"effectType":0,"warning":0,"unlockWay":[0,0],"hurt":[50,50],"shootSpeed":[500,500],"hitAudioId":[],"bulletType":[3,-90],"attackRange":[600,1000],"qte":[0,0],"duration":[0]},"321":{"id":321,"name":"石头多方向连发","weaponType":2,"bulletNum":15,"chamber":3.5,"scatterRatio":0.4,"shootDelta":0.05,"singleNum":16,"resPath":"weapon111","hurtRange":0,"isCross":0,"bulletId":44,"showPos":2,"fireAudioId":111,"hitEffectId":111,"fireEffectId":0,"dropId":1011,"sortIndex":0,"hitBack":0,"effectType":4,"warning":0,"unlockWay":[0,0],"hurt":[50,50],"shootSpeed":[400,400],"hitAudioId":[],"bulletType":[0,0],"attackRange":[600,1000],"qte":[0,0],"duration":[0]},"322":{"id":322,"name":"蝙蝠螺旋子弹65","weaponType":2,"bulletNum":70,"chamber":2,"scatterRatio":0,"shootDelta":0.05,"singleNum":1,"resPath":"weapon301","hurtRange":0,"isCross":0,"bulletId":43,"showPos":2,"fireAudioId":0,"hitEffectId":0,"fireEffectId":0,"dropId":1001,"sortIndex":0,"hitBack":0,"effectType":0,"warning":0,"unlockWay":[0,0],"hurt":[50,50],"shootSpeed":[200,500,1],"hitAudioId":[],"bulletType":[3,-360],"attackRange":[500,1000],"qte":[0,0],"duration":[0]},"323":{"id":323,"name":"茂盛树65","weaponType":2,"bulletNum":5,"chamber":2,"scatterRatio":0.3,"shootDelta":0.7,"singleNum":8,"resPath":"weapon301","hurtRange":0,"isCross":0,"bulletId":43,"showPos":2,"fireAudioId":0,"hitEffectId":0,"fireEffectId":0,"dropId":1001,"sortIndex":0,"hitBack":0,"effectType":0,"warning":0,"unlockWay":[0,0],"hurt":[50,50],"shootSpeed":[500,500],"hitAudioId":[],"bulletType":[0,100],"attackRange":[500,1000],"qte":[0,0],"duration":[0]},"324":{"id":324,"name":"茂盛树65","weaponType":2,"bulletNum":70,"chamber":2,"scatterRatio":0,"shootDelta":0.05,"singleNum":1,"resPath":"weapon301","hurtRange":0,"isCross":0,"bulletId":43,"showPos":2,"fireAudioId":0,"hitEffectId":0,"fireEffectId":0,"dropId":1001,"sortIndex":0,"hitBack":0,"effectType":0,"warning":0,"unlockWay":[0,0],"hurt":[50,50],"shootSpeed":[200,500,1],"hitAudioId":[],"bulletType":[3,360],"attackRange":[500,1000],"qte":[0,0],"duration":[0]},"325":{"id":325,"name":"机器人激光70","weaponType":2,"bulletNum":99999999,"chamber":0,"scatterRatio":0,"shootDelta":2,"singleNum":1,"resPath":"weapon301","hurtRange":0,"isCross":1,"bulletId":45,"showPos":2,"fireAudioId":0,"hitEffectId":0,"fireEffectId":0,"dropId":1001,"sortIndex":0,"hitBack":0,"effectType":0,"warning":1,"unlockWay":[0,0],"hurt":[50,50],"shootSpeed":[4000,4000],"hitAudioId":[],"bulletType":[0,100],"attackRange":[500,1000],"qte":[0,0],"duration":[0]},"326":{"id":326,"name":"机器人70","weaponType":2,"bulletNum":99999999,"chamber":0,"scatterRatio":0.3,"shootDelta":1.5,"singleNum":3,"resPath":"weapon301","hurtRange":0,"isCross":1,"bulletId":45,"showPos":2,"fireAudioId":0,"hitEffectId":0,"fireEffectId":0,"dropId":1001,"sortIndex":0,"hitBack":0,"effectType":0,"warning":0.9,"unlockWay":[0,0],"hurt":[50,50],"shootSpeed":[4000,4000],"hitAudioId":[],"bulletType":[0,100],"attackRange":[500,1000],"qte":[0,0],"duration":[0]},"327":{"id":327,"name":"机器人70","weaponType":2,"bulletNum":99999999,"chamber":0,"scatterRatio":0.4,"shootDelta":1.5,"singleNum":16,"resPath":"weapon301","hurtRange":0,"isCross":1,"bulletId":45,"showPos":2,"fireAudioId":0,"hitEffectId":0,"fireEffectId":0,"dropId":1001,"sortIndex":0,"hitBack":0,"effectType":0,"warning":0.8,"unlockWay":[0,0],"hurt":[50,50],"shootSpeed":[4000,4000],"hitAudioId":[],"bulletType":[0,100],"attackRange":[500,1000],"qte":[0,0],"duration":[0]},"328":{"id":328,"name":"喷火龙两次三连发75","weaponType":2,"bulletNum":99999,"chamber":0.6,"scatterRatio":0.3,"shootDelta":1.5,"singleNum":3,"resPath":"weapon105","hurtRange":0,"isCross":0,"bulletId":40,"showPos":2,"fireAudioId":121,"hitEffectId":110,"fireEffectId":0,"dropId":1005,"sortIndex":0,"hitBack":0,"effectType":2,"warning":0,"unlockWay":[0,0],"hurt":[50,50],"shootSpeed":[500,500],"hitAudioId":[],"bulletType":[0,30],"attackRange":[500,1000],"qte":[0,0],"duration":[0]},"329":{"id":329,"name":"喷火龙火柱75","weaponType":2,"bulletNum":10,"chamber":1,"scatterRatio":0,"shootDelta":0.1,"singleNum":1,"resPath":"weapon111","hurtRange":0,"isCross":0,"bulletId":40,"showPos":2,"fireAudioId":111,"hitEffectId":111,"fireEffectId":0,"dropId":1011,"sortIndex":0,"hitBack":0,"effectType":4,"warning":0,"unlockWay":[0,0],"hurt":[50,50],"shootSpeed":[450,450],"hitAudioId":[],"bulletType":[1,250],"attackRange":[500,1000],"qte":[0,0],"duration":[0]},"330":{"id":330,"name":"喷火龙8个方向三连发75","weaponType":2,"bulletNum":3,"chamber":1.5,"scatterRatio":0.78,"shootDelta":0.2,"singleNum":8,"resPath":"weapon105","hurtRange":0,"isCross":0,"bulletId":40,"showPos":2,"fireAudioId":121,"hitEffectId":110,"fireEffectId":0,"dropId":1005,"sortIndex":0,"hitBack":0,"effectType":2,"warning":0,"unlockWay":[0,0],"hurt":[50,50],"shootSpeed":[500,500],"hitAudioId":[],"bulletType":[0,30],"attackRange":[500,1000],"qte":[0,0],"duration":[0]},"331":{"id":331,"name":"四脚石头80","weaponType":2,"bulletNum":40,"chamber":2,"scatterRatio":3.14,"shootDelta":0.1,"singleNum":2,"resPath":"weapon301","hurtRange":0,"isCross":0,"bulletId":28,"showPos":2,"fireAudioId":0,"hitEffectId":0,"fireEffectId":0,"dropId":1001,"sortIndex":0,"hitBack":0,"effectType":0,"warning":0,"unlockWay":[0,0],"hurt":[50,50],"shootSpeed":[500,500],"hitAudioId":[],"bulletType":[3,90],"attackRange":[500,1000],"qte":[0,0],"duration":[0]},"332":{"id":332,"name":"四脚石头80","weaponType":2,"bulletNum":5,"chamber":2,"scatterRatio":1.57,"shootDelta":0.5,"singleNum":4,"resPath":"weapon301","hurtRange":0,"isCross":0,"bulletId":28,"showPos":2,"fireAudioId":0,"hitEffectId":0,"fireEffectId":0,"dropId":1001,"sortIndex":0,"hitBack":0,"effectType":0,"warning":0,"unlockWay":[0,0],"hurt":[50,50],"shootSpeed":[600,600],"hitAudioId":[],"bulletType":[0,100],"attackRange":[500,1000],"qte":[0,0],"duration":[0]},"333":{"id":333,"name":"四脚石头80","weaponType":2,"bulletNum":5,"chamber":3,"scatterRatio":0.34,"shootDelta":0.3,"singleNum":18,"resPath":"weapon301","hurtRange":0,"isCross":0,"bulletId":28,"showPos":2,"fireAudioId":0,"hitEffectId":0,"fireEffectId":0,"dropId":1001,"sortIndex":0,"hitBack":0,"effectType":0,"warning":0,"unlockWay":[0,0],"hurt":[50,50],"shootSpeed":[500,500],"hitAudioId":[],"bulletType":[0,100],"attackRange":[500,1000],"qte":[0,0],"duration":[0]},"334":{"id":334,"name":"蝙蝠5个方向快速子弹85","weaponType":2,"bulletNum":5,"chamber":1.5,"scatterRatio":0.5,"shootDelta":0.1,"singleNum":5,"resPath":"weapon105","hurtRange":0,"isCross":0,"bulletId":43,"showPos":2,"fireAudioId":121,"hitEffectId":110,"fireEffectId":0,"dropId":1005,"sortIndex":0,"hitBack":0,"effectType":2,"warning":0,"unlockWay":[0,0],"hurt":[50,50],"shootSpeed":[600,600],"hitAudioId":[],"bulletType":[1,100],"attackRange":[500,1000],"qte":[0,0],"duration":[0]},"335":{"id":335,"name":"5个方向旋转大风车85","weaponType":2,"bulletNum":15,"chamber":2,"scatterRatio":1.25,"shootDelta":0.2,"singleNum":5,"resPath":"weapon105","hurtRange":0,"isCross":0,"bulletId":44,"showPos":2,"fireAudioId":121,"hitEffectId":110,"fireEffectId":0,"dropId":1005,"sortIndex":0,"hitBack":0,"effectType":2,"warning":0,"unlockWay":[0,0],"hurt":[50,50],"shootSpeed":[500,500],"hitAudioId":[],"bulletType":[3,50],"attackRange":[500,1000],"qte":[1,336],"duration":[[3,3]]},"336":{"id":336,"name":"单个条密集子弹85","weaponType":2,"bulletNum":9999,"chamber":0,"scatterRatio":0,"shootDelta":0.1,"singleNum":1,"resPath":"weapon111","hurtRange":0,"isCross":0,"bulletId":43,"showPos":2,"fireAudioId":111,"hitEffectId":111,"fireEffectId":0,"dropId":1011,"sortIndex":0,"hitBack":0,"effectType":4,"warning":0,"unlockWay":[0,0],"hurt":[50,50],"shootSpeed":[450,450],"hitAudioId":[],"bulletType":[1,360],"attackRange":[500,1000],"qte":[0,0],"duration":[0]},"337":{"id":337,"name":"三连发激光85","weaponType":2,"bulletNum":3,"chamber":2,"scatterRatio":0,"shootDelta":0.6,"singleNum":1,"resPath":"weapon112","hurtRange":0,"isCross":1,"bulletId":45,"showPos":2,"fireAudioId":112,"hitEffectId":0,"fireEffectId":0,"dropId":1012,"sortIndex":0,"hitBack":0,"effectType":6,"warning":0.4,"unlockWay":[0,0],"hurt":[50,50],"shootSpeed":[4000,4000],"hitAudioId":[],"bulletType":[0,100],"attackRange":[500,1000],"qte":[0,0],"duration":[0]},"338":{"id":338,"name":"15发360发射90","weaponType":2,"bulletNum":8,"chamber":1.5,"scatterRatio":0.418,"shootDelta":0.5,"singleNum":15,"resPath":"weapon112","hurtRange":0,"isCross":0,"bulletId":43,"showPos":2,"fireAudioId":112,"hitEffectId":0,"fireEffectId":0,"dropId":1012,"sortIndex":0,"hitBack":0,"effectType":6,"warning":0,"unlockWay":[0,0],"hurt":[50,50],"shootSpeed":[400,400],"hitAudioId":[],"bulletType":[1,300],"attackRange":[500,1000],"qte":[0,0],"duration":[0]},"339":{"id":339,"name":"boss树木攻击90","weaponType":2,"bulletNum":7,"chamber":2,"scatterRatio":1.04,"shootDelta":0.1,"singleNum":6,"resPath":"weapon301","hurtRange":0,"isCross":0,"bulletId":44,"showPos":2,"fireAudioId":0,"hitEffectId":0,"fireEffectId":0,"dropId":1001,"sortIndex":0,"hitBack":0,"effectType":0,"warning":0,"unlockWay":[0,0],"hurt":[50,50],"shootSpeed":[400,400],"hitAudioId":[],"bulletType":[3,40],"attackRange":[500,1000],"qte":[1,339],"duration":[[2,0.7]]},"340":{"id":340,"name":"boss树木攻击90","weaponType":2,"bulletNum":30,"chamber":2,"scatterRatio":1.04,"shootDelta":0.1,"singleNum":6,"resPath":"weapon301","hurtRange":0,"isCross":0,"bulletId":44,"showPos":2,"fireAudioId":0,"hitEffectId":0,"fireEffectId":0,"dropId":1001,"sortIndex":0,"hitBack":0,"effectType":0,"warning":0,"unlockWay":[0,0],"hurt":[50,50],"shootSpeed":[400,400],"hitAudioId":[],"bulletType":[3,-40],"attackRange":[500,1000],"qte":[0,0],"duration":[0]},"341":{"id":341,"name":"大风车95","weaponType":2,"bulletNum":30,"chamber":2,"scatterRatio":2.09,"shootDelta":0.1,"singleNum":3,"resPath":"weapon112","hurtRange":0,"isCross":0,"bulletId":43,"showPos":2,"fireAudioId":112,"hitEffectId":0,"fireEffectId":0,"dropId":1012,"sortIndex":0,"hitBack":0,"effectType":6,"warning":0,"unlockWay":[0,0],"hurt":[50,50],"shootSpeed":[500,500],"hitAudioId":[],"bulletType":[3,-40],"attackRange":[500,1000],"qte":[0,0],"duration":[0]},"342":{"id":342,"name":"大风车95","weaponType":2,"bulletNum":30,"chamber":2,"scatterRatio":1.25,"shootDelta":0.1,"singleNum":5,"resPath":"weapon112","hurtRange":0,"isCross":0,"bulletId":43,"showPos":2,"fireAudioId":112,"hitEffectId":0,"fireEffectId":0,"dropId":1012,"sortIndex":0,"hitBack":0,"effectType":6,"warning":0,"unlockWay":[0,0],"hurt":[50,50],"shootSpeed":[500,500],"hitAudioId":[],"bulletType":[3,40],"attackRange":[500,1000],"qte":[0,0],"duration":[0]},"343":{"id":343,"name":"大风车95","weaponType":2,"bulletNum":20,"chamber":1,"scatterRatio":0.785,"shootDelta":0.1,"singleNum":8,"resPath":"weapon112","hurtRange":0,"isCross":0,"bulletId":43,"showPos":2,"fireAudioId":112,"hitEffectId":0,"fireEffectId":0,"dropId":1012,"sortIndex":0,"hitBack":0,"effectType":6,"warning":0,"unlockWay":[0,0],"hurt":[50,50],"shootSpeed":[500,500],"hitAudioId":[],"bulletType":[3,-30],"attackRange":[500,1000],"qte":[0,0],"duration":[0]},"344":{"id":344,"name":"蝙蝠螺旋子弹100","weaponType":2,"bulletNum":9999,"chamber":0,"scatterRatio":0,"shootDelta":0.05,"singleNum":1,"resPath":"weapon301","hurtRange":0,"isCross":0,"bulletId":43,"showPos":2,"fireAudioId":0,"hitEffectId":0,"fireEffectId":0,"dropId":1001,"sortIndex":0,"hitBack":0,"effectType":0,"warning":0,"unlockWay":[0,0],"hurt":[50,50],"shootSpeed":[200,500,1],"hitAudioId":[],"bulletType":[3,-360],"attackRange":[500,1000],"qte":[0,0],"duration":[0]},"345":{"id":345,"name":"茂盛树100","weaponType":2,"bulletNum":99999999,"chamber":0,"scatterRatio":0.3,"shootDelta":1,"singleNum":8,"resPath":"weapon301","hurtRange":0,"isCross":0,"bulletId":43,"showPos":2,"fireAudioId":0,"hitEffectId":0,"fireEffectId":0,"dropId":1001,"sortIndex":0,"hitBack":0,"effectType":0,"warning":0,"unlockWay":[0,0],"hurt":[50,50],"shootSpeed":[500,500],"hitAudioId":[],"bulletType":[0,100],"attackRange":[500,1000],"qte":[0,0],"duration":[0]},"346":{"id":346,"name":"茂盛树100","weaponType":2,"bulletNum":9999,"chamber":0,"scatterRatio":0,"shootDelta":0.05,"singleNum":1,"resPath":"weapon301","hurtRange":0,"isCross":0,"bulletId":43,"showPos":2,"fireAudioId":0,"hitEffectId":0,"fireEffectId":0,"dropId":1001,"sortIndex":0,"hitBack":0,"effectType":0,"warning":0,"unlockWay":[0,0],"hurt":[50,50],"shootSpeed":[200,500,1],"hitAudioId":[],"bulletType":[3,360],"attackRange":[500,1000],"qte":[1,347],"duration":[[1,9999]]},"347":{"id":347,"name":"蝙蝠螺旋子弹100","weaponType":2,"bulletNum":9999,"chamber":0,"scatterRatio":0,"shootDelta":0.05,"singleNum":1,"resPath":"weapon301","hurtRange":0,"isCross":0,"bulletId":43,"showPos":2,"fireAudioId":0,"hitEffectId":0,"fireEffectId":0,"dropId":1001,"sortIndex":0,"hitBack":0,"effectType":0,"warning":0,"unlockWay":[0,0],"hurt":[50,50],"shootSpeed":[200,500,1],"hitAudioId":[],"bulletType":[3,-360],"attackRange":[500,1000],"qte":[0,0],"duration":[0]},"348":{"id":348,"name":"喷火龙两次三连发105","weaponType":2,"bulletNum":3,"chamber":0.8,"scatterRatio":0.3,"shootDelta":0.5,"singleNum":3,"resPath":"weapon105","hurtRange":0,"isCross":0,"bulletId":40,"showPos":2,"fireAudioId":121,"hitEffectId":110,"fireEffectId":0,"dropId":1005,"sortIndex":0,"hitBack":0,"effectType":2,"warning":0,"unlockWay":[0,0],"hurt":[50,50],"shootSpeed":[500,500],"hitAudioId":[],"bulletType":[0,30],"attackRange":[500,1000],"qte":[0,0],"duration":[0]},"349":{"id":349,"name":"喷火龙火柱105","weaponType":2,"bulletNum":10,"chamber":0.8,"scatterRatio":0,"shootDelta":0.1,"singleNum":1,"resPath":"weapon111","hurtRange":0,"isCross":0,"bulletId":40,"showPos":2,"fireAudioId":111,"hitEffectId":111,"fireEffectId":0,"dropId":1011,"sortIndex":0,"hitBack":0,"effectType":4,"warning":0,"unlockWay":[0,0],"hurt":[50,50],"shootSpeed":[450,450],"hitAudioId":[],"bulletType":[1,250],"attackRange":[500,1000],"qte":[0,0],"duration":[0]},"350":{"id":350,"name":"喷火龙8个方向三连发105","weaponType":2,"bulletNum":5,"chamber":1.5,"scatterRatio":0.78,"shootDelta":0.2,"singleNum":8,"resPath":"weapon105","hurtRange":0,"isCross":0,"bulletId":40,"showPos":2,"fireAudioId":121,"hitEffectId":110,"fireEffectId":0,"dropId":1005,"sortIndex":0,"hitBack":0,"effectType":2,"warning":0,"unlockWay":[0,0],"hurt":[50,50],"shootSpeed":[500,500],"hitAudioId":[],"bulletType":[0,30],"attackRange":[500,1000],"qte":[0,0],"duration":[0]},"351":{"id":351,"name":"四脚石头110","weaponType":2,"bulletNum":40,"chamber":2,"scatterRatio":3.14,"shootDelta":0.1,"singleNum":2,"resPath":"weapon301","hurtRange":0,"isCross":0,"bulletId":28,"showPos":2,"fireAudioId":0,"hitEffectId":0,"fireEffectId":0,"dropId":1001,"sortIndex":0,"hitBack":0,"effectType":0,"warning":0,"unlockWay":[0,0],"hurt":[50,50],"shootSpeed":[500,500],"hitAudioId":[],"bulletType":[3,90],"attackRange":[500,1000],"qte":[0,0],"duration":[0]},"352":{"id":352,"name":"四脚石头110","weaponType":2,"bulletNum":5,"chamber":2,"scatterRatio":1.57,"shootDelta":0.5,"singleNum":4,"resPath":"weapon301","hurtRange":0,"isCross":0,"bulletId":28,"showPos":2,"fireAudioId":0,"hitEffectId":0,"fireEffectId":0,"dropId":1001,"sortIndex":0,"hitBack":0,"effectType":0,"warning":0,"unlockWay":[0,0],"hurt":[50,50],"shootSpeed":[600,600],"hitAudioId":[],"bulletType":[0,100],"attackRange":[500,1000],"qte":[0,0],"duration":[0]},"353":{"id":353,"name":"四脚石头110","weaponType":2,"bulletNum":10,"chamber":2,"scatterRatio":0.34,"shootDelta":0.4,"singleNum":18,"resPath":"weapon301","hurtRange":0,"isCross":0,"bulletId":28,"showPos":2,"fireAudioId":0,"hitEffectId":0,"fireEffectId":0,"dropId":1001,"sortIndex":0,"hitBack":0,"effectType":0,"warning":0,"unlockWay":[0,0],"hurt":[50,50],"shootSpeed":[500,500],"hitAudioId":[],"bulletType":[0,100],"attackRange":[500,1000],"qte":[0,0],"duration":[0]},"354":{"id":354,"name":"15发360发射115","weaponType":2,"bulletNum":8,"chamber":2,"scatterRatio":0.418,"shootDelta":0.5,"singleNum":15,"resPath":"weapon112","hurtRange":0,"isCross":0,"bulletId":43,"showPos":2,"fireAudioId":112,"hitEffectId":0,"fireEffectId":0,"dropId":1012,"sortIndex":0,"hitBack":0,"effectType":6,"warning":0,"unlockWay":[0,0],"hurt":[50,50],"shootSpeed":[400,400],"hitAudioId":[],"bulletType":[1,300],"attackRange":[500,1000],"qte":[0,0],"duration":[0]},"355":{"id":355,"name":"boss树木攻击115","weaponType":2,"bulletNum":7,"chamber":2,"scatterRatio":1.04,"shootDelta":0.1,"singleNum":6,"resPath":"weapon301","hurtRange":0,"isCross":0,"bulletId":44,"showPos":2,"fireAudioId":0,"hitEffectId":0,"fireEffectId":0,"dropId":1001,"sortIndex":0,"hitBack":0,"effectType":0,"warning":0,"unlockWay":[0,0],"hurt":[50,50],"shootSpeed":[400,400],"hitAudioId":[],"bulletType":[3,40],"attackRange":[500,1000],"qte":[1,355],"duration":[[2,0.7]]},"356":{"id":356,"name":"boss树木攻击115","weaponType":2,"bulletNum":999,"chamber":0,"scatterRatio":1.04,"shootDelta":0.1,"singleNum":6,"resPath":"weapon301","hurtRange":0,"isCross":0,"bulletId":44,"showPos":2,"fireAudioId":0,"hitEffectId":0,"fireEffectId":0,"dropId":1001,"sortIndex":0,"hitBack":0,"effectType":0,"warning":0,"unlockWay":[0,0],"hurt":[50,50],"shootSpeed":[400,400],"hitAudioId":[],"bulletType":[3,-40],"attackRange":[500,1000],"qte":[0,0],"duration":[0]},"357":{"id":357,"name":"大风车120","weaponType":2,"bulletNum":9999,"chamber":0,"scatterRatio":2.09,"shootDelta":0.1,"singleNum":3,"resPath":"weapon112","hurtRange":0,"isCross":0,"bulletId":43,"showPos":2,"fireAudioId":112,"hitEffectId":0,"fireEffectId":0,"dropId":1012,"sortIndex":0,"hitBack":0,"effectType":6,"warning":0,"unlockWay":[0,0],"hurt":[50,50],"shootSpeed":[500,500],"hitAudioId":[],"bulletType":[3,-40],"attackRange":[500,1000],"qte":[0,0],"duration":[0]},"358":{"id":358,"name":"大风车120","weaponType":2,"bulletNum":9999,"chamber":0,"scatterRatio":1.25,"shootDelta":0.1,"singleNum":5,"resPath":"weapon112","hurtRange":0,"isCross":0,"bulletId":43,"showPos":2,"fireAudioId":112,"hitEffectId":0,"fireEffectId":0,"dropId":1012,"sortIndex":0,"hitBack":0,"effectType":6,"warning":0,"unlockWay":[0,0],"hurt":[50,50],"shootSpeed":[500,500],"hitAudioId":[],"bulletType":[3,40],"attackRange":[500,1000],"qte":[0,0],"duration":[0]},"359":{"id":359,"name":"大风车120","weaponType":2,"bulletNum":20,"chamber":1,"scatterRatio":0.785,"shootDelta":0.1,"singleNum":8,"resPath":"weapon112","hurtRange":0,"isCross":0,"bulletId":43,"showPos":2,"fireAudioId":112,"hitEffectId":0,"fireEffectId":0,"dropId":1012,"sortIndex":0,"hitBack":0,"effectType":6,"warning":0,"unlockWay":[0,0],"hurt":[50,50],"shootSpeed":[500,500],"hitAudioId":[],"bulletType":[3,-30],"attackRange":[500,1000],"qte":[0,0],"duration":[0]},"360":{"id":360,"name":"蝙蝠螺旋子弹125","weaponType":2,"bulletNum":9999,"chamber":0,"scatterRatio":0,"shootDelta":0.05,"singleNum":1,"resPath":"weapon301","hurtRange":0,"isCross":0,"bulletId":43,"showPos":2,"fireAudioId":0,"hitEffectId":0,"fireEffectId":0,"dropId":1001,"sortIndex":0,"hitBack":0,"effectType":0,"warning":0,"unlockWay":[0,0],"hurt":[50,50],"shootSpeed":[200,500,1],"hitAudioId":[],"bulletType":[3,-360],"attackRange":[500,1000],"qte":[0,0],"duration":[0]},"361":{"id":361,"name":"茂盛树125","weaponType":2,"bulletNum":99999999,"chamber":0,"scatterRatio":0.3,"shootDelta":1,"singleNum":8,"resPath":"weapon301","hurtRange":0,"isCross":0,"bulletId":43,"showPos":2,"fireAudioId":0,"hitEffectId":0,"fireEffectId":0,"dropId":1001,"sortIndex":0,"hitBack":0,"effectType":0,"warning":0,"unlockWay":[0,0],"hurt":[50,50],"shootSpeed":[500,500],"hitAudioId":[],"bulletType":[0,100],"attackRange":[500,1000],"qte":[0,0],"duration":[0]},"362":{"id":362,"name":"茂盛树125","weaponType":2,"bulletNum":9999,"chamber":0,"scatterRatio":0,"shootDelta":0.05,"singleNum":1,"resPath":"weapon301","hurtRange":0,"isCross":0,"bulletId":43,"showPos":2,"fireAudioId":0,"hitEffectId":0,"fireEffectId":0,"dropId":1001,"sortIndex":0,"hitBack":0,"effectType":0,"warning":0,"unlockWay":[0,0],"hurt":[50,50],"shootSpeed":[200,500,1],"hitAudioId":[],"bulletType":[3,360],"attackRange":[500,1000],"qte":[1,363],"duration":[[1,9999]]},"363":{"id":363,"name":"蝙蝠螺旋子弹125","weaponType":2,"bulletNum":9999,"chamber":0,"scatterRatio":0,"shootDelta":0.05,"singleNum":1,"resPath":"weapon301","hurtRange":0,"isCross":0,"bulletId":43,"showPos":2,"fireAudioId":0,"hitEffectId":0,"fireEffectId":0,"dropId":1001,"sortIndex":0,"hitBack":0,"effectType":0,"warning":0,"unlockWay":[0,0],"hurt":[50,50],"shootSpeed":[200,500,1],"hitAudioId":[],"bulletType":[3,-360],"attackRange":[500,1000],"qte":[0,0],"duration":[0]},"364":{"id":364,"name":"喷火龙两次三连发130","weaponType":2,"bulletNum":3,"chamber":0.8,"scatterRatio":0.3,"shootDelta":0.5,"singleNum":3,"resPath":"weapon105","hurtRange":0,"isCross":0,"bulletId":40,"showPos":2,"fireAudioId":121,"hitEffectId":110,"fireEffectId":0,"dropId":1005,"sortIndex":0,"hitBack":0,"effectType":2,"warning":0,"unlockWay":[0,0],"hurt":[50,50],"shootSpeed":[500,500],"hitAudioId":[],"bulletType":[0,30],"attackRange":[500,1000],"qte":[0,0],"duration":[0]},"365":{"id":365,"name":"喷火龙火柱130","weaponType":2,"bulletNum":10,"chamber":0.8,"scatterRatio":0,"shootDelta":0.1,"singleNum":1,"resPath":"weapon111","hurtRange":0,"isCross":0,"bulletId":40,"showPos":2,"fireAudioId":111,"hitEffectId":111,"fireEffectId":0,"dropId":1011,"sortIndex":0,"hitBack":0,"effectType":4,"warning":0,"unlockWay":[0,0],"hurt":[50,50],"shootSpeed":[450,450],"hitAudioId":[],"bulletType":[1,250],"attackRange":[500,1000],"qte":[0,0],"duration":[0]},"366":{"id":366,"name":"喷火龙8个方向三连发130","weaponType":2,"bulletNum":5,"chamber":1.5,"scatterRatio":0.78,"shootDelta":0.2,"singleNum":8,"resPath":"weapon105","hurtRange":0,"isCross":0,"bulletId":40,"showPos":2,"fireAudioId":121,"hitEffectId":110,"fireEffectId":0,"dropId":1005,"sortIndex":0,"hitBack":0,"effectType":2,"warning":0,"unlockWay":[0,0],"hurt":[50,50],"shootSpeed":[500,500],"hitAudioId":[],"bulletType":[0,30],"attackRange":[500,1000],"qte":[0,0],"duration":[0]},"367":{"id":367,"name":"四脚石头135","weaponType":2,"bulletNum":40,"chamber":2,"scatterRatio":3.14,"shootDelta":0.1,"singleNum":2,"resPath":"weapon301","hurtRange":0,"isCross":0,"bulletId":28,"showPos":2,"fireAudioId":0,"hitEffectId":0,"fireEffectId":0,"dropId":1001,"sortIndex":0,"hitBack":0,"effectType":0,"warning":0,"unlockWay":[0,0],"hurt":[50,50],"shootSpeed":[500,500],"hitAudioId":[],"bulletType":[3,90],"attackRange":[500,1000],"qte":[0,0],"duration":[0]},"368":{"id":368,"name":"四脚石头135","weaponType":2,"bulletNum":5,"chamber":2,"scatterRatio":1.57,"shootDelta":0.5,"singleNum":4,"resPath":"weapon301","hurtRange":0,"isCross":0,"bulletId":28,"showPos":2,"fireAudioId":0,"hitEffectId":0,"fireEffectId":0,"dropId":1001,"sortIndex":0,"hitBack":0,"effectType":0,"warning":0,"unlockWay":[0,0],"hurt":[50,50],"shootSpeed":[600,600],"hitAudioId":[],"bulletType":[0,100],"attackRange":[500,1000],"qte":[0,0],"duration":[0]},"369":{"id":369,"name":"四脚石头135","weaponType":2,"bulletNum":20,"chamber":3,"scatterRatio":0.34,"shootDelta":0.3,"singleNum":18,"resPath":"weapon301","hurtRange":0,"isCross":0,"bulletId":28,"showPos":2,"fireAudioId":0,"hitEffectId":0,"fireEffectId":0,"dropId":1001,"sortIndex":0,"hitBack":0,"effectType":0,"warning":0,"unlockWay":[0,0],"hurt":[50,50],"shootSpeed":[500,500],"hitAudioId":[],"bulletType":[0,100],"attackRange":[500,1000],"qte":[0,0],"duration":[0]},"370":{"id":370,"name":"15发360发射140","weaponType":2,"bulletNum":8,"chamber":1.5,"scatterRatio":0.418,"shootDelta":0.5,"singleNum":15,"resPath":"weapon112","hurtRange":0,"isCross":0,"bulletId":43,"showPos":2,"fireAudioId":112,"hitEffectId":0,"fireEffectId":0,"dropId":1012,"sortIndex":0,"hitBack":0,"effectType":6,"warning":0,"unlockWay":[0,0],"hurt":[50,50],"shootSpeed":[400,400],"hitAudioId":[],"bulletType":[1,300],"attackRange":[500,1000],"qte":[0,0],"duration":[0]},"371":{"id":371,"name":"boss树木攻击140","weaponType":2,"bulletNum":7,"chamber":2,"scatterRatio":1.04,"shootDelta":0.1,"singleNum":6,"resPath":"weapon301","hurtRange":0,"isCross":0,"bulletId":44,"showPos":2,"fireAudioId":0,"hitEffectId":0,"fireEffectId":0,"dropId":1001,"sortIndex":0,"hitBack":0,"effectType":0,"warning":0,"unlockWay":[0,0],"hurt":[50,50],"shootSpeed":[400,400],"hitAudioId":[],"bulletType":[3,40],"attackRange":[500,1000],"qte":[1,371],"duration":[[2,0.7]]},"372":{"id":372,"name":"boss树木攻击140","weaponType":2,"bulletNum":999,"chamber":0,"scatterRatio":1.04,"shootDelta":0.1,"singleNum":6,"resPath":"weapon301","hurtRange":0,"isCross":0,"bulletId":44,"showPos":2,"fireAudioId":0,"hitEffectId":0,"fireEffectId":0,"dropId":1001,"sortIndex":0,"hitBack":0,"effectType":0,"warning":0,"unlockWay":[0,0],"hurt":[50,50],"shootSpeed":[400,400],"hitAudioId":[],"bulletType":[3,-40],"attackRange":[500,1000],"qte":[0,0],"duration":[0]},"373":{"id":373,"name":"大风车145","weaponType":2,"bulletNum":9999,"chamber":0,"scatterRatio":2.09,"shootDelta":0.1,"singleNum":3,"resPath":"weapon112","hurtRange":0,"isCross":0,"bulletId":43,"showPos":2,"fireAudioId":112,"hitEffectId":0,"fireEffectId":0,"dropId":1012,"sortIndex":0,"hitBack":0,"effectType":6,"warning":0,"unlockWay":[0,0],"hurt":[50,50],"shootSpeed":[500,500],"hitAudioId":[],"bulletType":[3,-40],"attackRange":[500,1000],"qte":[0,0],"duration":[0]},"374":{"id":374,"name":"大风车145","weaponType":2,"bulletNum":9999,"chamber":0,"scatterRatio":1.25,"shootDelta":0.1,"singleNum":5,"resPath":"weapon112","hurtRange":0,"isCross":0,"bulletId":43,"showPos":2,"fireAudioId":112,"hitEffectId":0,"fireEffectId":0,"dropId":1012,"sortIndex":0,"hitBack":0,"effectType":6,"warning":0,"unlockWay":[0,0],"hurt":[50,50],"shootSpeed":[500,500],"hitAudioId":[],"bulletType":[3,40],"attackRange":[500,1000],"qte":[0,0],"duration":[0]},"375":{"id":375,"name":"大风车145","weaponType":2,"bulletNum":20,"chamber":1,"scatterRatio":0.785,"shootDelta":0.1,"singleNum":8,"resPath":"weapon112","hurtRange":0,"isCross":0,"bulletId":43,"showPos":2,"fireAudioId":112,"hitEffectId":0,"fireEffectId":0,"dropId":1012,"sortIndex":0,"hitBack":0,"effectType":6,"warning":0,"unlockWay":[0,0],"hurt":[50,50],"shootSpeed":[500,500],"hitAudioId":[],"bulletType":[3,-30],"attackRange":[500,1000],"qte":[0,0],"duration":[0]},"376":{"id":376,"name":"蝙蝠螺旋子弹150","weaponType":2,"bulletNum":9999,"chamber":0,"scatterRatio":0,"shootDelta":0.05,"singleNum":1,"resPath":"weapon301","hurtRange":0,"isCross":0,"bulletId":43,"showPos":2,"fireAudioId":0,"hitEffectId":0,"fireEffectId":0,"dropId":1001,"sortIndex":0,"hitBack":0,"effectType":0,"warning":0,"unlockWay":[0,0],"hurt":[50,50],"shootSpeed":[350,350],"hitAudioId":[],"bulletType":[3,-360],"attackRange":[500,1000],"qte":[0,0],"duration":[0]},"377":{"id":377,"name":"茂盛树150","weaponType":2,"bulletNum":99999999,"chamber":0,"scatterRatio":0.3,"shootDelta":1,"singleNum":8,"resPath":"weapon301","hurtRange":0,"isCross":0,"bulletId":43,"showPos":2,"fireAudioId":0,"hitEffectId":0,"fireEffectId":0,"dropId":1001,"sortIndex":0,"hitBack":0,"effectType":0,"warning":0,"unlockWay":[0,0],"hurt":[50,50],"shootSpeed":[500,500],"hitAudioId":[],"bulletType":[0,100],"attackRange":[500,1000],"qte":[0,0],"duration":[0]},"378":{"id":378,"name":"茂盛树150","weaponType":2,"bulletNum":9999,"chamber":0,"scatterRatio":0,"shootDelta":0.05,"singleNum":1,"resPath":"weapon301","hurtRange":0,"isCross":0,"bulletId":43,"showPos":2,"fireAudioId":0,"hitEffectId":0,"fireEffectId":0,"dropId":1001,"sortIndex":0,"hitBack":0,"effectType":0,"warning":0,"unlockWay":[0,0],"hurt":[50,50],"shootSpeed":[200,500,1],"hitAudioId":[],"bulletType":[3,360],"attackRange":[500,1000],"qte":[1,379],"duration":[[1,9999]]},"379":{"id":379,"name":"蝙蝠螺旋子弹150","weaponType":2,"bulletNum":9999,"chamber":0,"scatterRatio":0,"shootDelta":0.05,"singleNum":1,"resPath":"weapon301","hurtRange":0,"isCross":0,"bulletId":43,"showPos":2,"fireAudioId":0,"hitEffectId":0,"fireEffectId":0,"dropId":1001,"sortIndex":0,"hitBack":0,"effectType":0,"warning":0,"unlockWay":[0,0],"hurt":[50,50],"shootSpeed":[200,500],"hitAudioId":[],"bulletType":[3,-360],"attackRange":[500,1000],"qte":[0,0],"duration":[0]},"380":{"id":380,"name":"喷火龙两次三连发155","weaponType":2,"bulletNum":3,"chamber":0.8,"scatterRatio":0.3,"shootDelta":0.5,"singleNum":3,"resPath":"weapon105","hurtRange":0,"isCross":0,"bulletId":40,"showPos":2,"fireAudioId":121,"hitEffectId":110,"fireEffectId":0,"dropId":1005,"sortIndex":0,"hitBack":0,"effectType":2,"warning":0,"unlockWay":[0,0],"hurt":[50,50],"shootSpeed":[500,500],"hitAudioId":[],"bulletType":[0,30],"attackRange":[500,1000],"qte":[0,0],"duration":[0]},"381":{"id":381,"name":"喷火龙火柱155","weaponType":2,"bulletNum":10,"chamber":0.8,"scatterRatio":0,"shootDelta":0.1,"singleNum":1,"resPath":"weapon111","hurtRange":0,"isCross":0,"bulletId":40,"showPos":2,"fireAudioId":111,"hitEffectId":111,"fireEffectId":0,"dropId":1011,"sortIndex":0,"hitBack":0,"effectType":4,"warning":0,"unlockWay":[0,0],"hurt":[50,50],"shootSpeed":[450,450],"hitAudioId":[],"bulletType":[1,250],"attackRange":[500,1000],"qte":[0,0],"duration":[0]},"382":{"id":382,"name":"喷火龙8个方向三连发155","weaponType":2,"bulletNum":5,"chamber":1.5,"scatterRatio":0.78,"shootDelta":0.2,"singleNum":8,"resPath":"weapon105","hurtRange":0,"isCross":0,"bulletId":40,"showPos":2,"fireAudioId":121,"hitEffectId":110,"fireEffectId":0,"dropId":1005,"sortIndex":0,"hitBack":0,"effectType":2,"warning":0,"unlockWay":[0,0],"hurt":[50,50],"shootSpeed":[500,500],"hitAudioId":[],"bulletType":[0,30],"attackRange":[500,1000],"qte":[0,0],"duration":[0]},"383":{"id":383,"name":"四脚石头20","weaponType":2,"bulletNum":40,"chamber":2,"scatterRatio":3.14,"shootDelta":0.1,"singleNum":2,"resPath":"weapon301","hurtRange":0,"isCross":0,"bulletId":28,"showPos":2,"fireAudioId":0,"hitEffectId":0,"fireEffectId":0,"dropId":1001,"sortIndex":0,"hitBack":0,"effectType":0,"warning":0,"unlockWay":[0,0],"hurt":[50,50],"shootSpeed":[500,500],"hitAudioId":[],"bulletType":[3,90],"attackRange":[500,1000],"qte":[0,0],"duration":[0]},"384":{"id":384,"name":"四脚石头20","weaponType":2,"bulletNum":5,"chamber":2,"scatterRatio":1.57,"shootDelta":0.5,"singleNum":4,"resPath":"weapon301","hurtRange":0,"isCross":0,"bulletId":28,"showPos":2,"fireAudioId":0,"hitEffectId":0,"fireEffectId":0,"dropId":1001,"sortIndex":0,"hitBack":0,"effectType":0,"warning":0,"unlockWay":[0,0],"hurt":[50,50],"shootSpeed":[600,600],"hitAudioId":[],"bulletType":[0,100],"attackRange":[500,1000],"qte":[0,0],"duration":[0]},"385":{"id":385,"name":"四脚石头20","weaponType":2,"bulletNum":10,"chamber":2,"scatterRatio":0.34,"shootDelta":0.4,"singleNum":18,"resPath":"weapon301","hurtRange":0,"isCross":0,"bulletId":28,"showPos":2,"fireAudioId":0,"hitEffectId":0,"fireEffectId":0,"dropId":1001,"sortIndex":0,"hitBack":0,"effectType":0,"warning":0,"unlockWay":[0,0],"hurt":[50,50],"shootSpeed":[500,500],"hitAudioId":[],"bulletType":[0,100],"attackRange":[500,1000],"qte":[0,0],"duration":[0]},"401":{"id":401,"name":"101大招","weaponType":6,"bulletNum":9999,"chamber":0,"scatterRatio":0,"shootDelta":0.1,"singleNum":11,"resPath":"weapon111","hurtRange":0,"isCross":0,"bulletId":47,"showPos":2,"fireAudioId":101,"hitEffectId":0,"fireEffectId":0,"dropId":1001,"sortIndex":0,"hitBack":0,"effectType":0,"warning":0,"unlockWay":[0,0],"hurt":[8,12],"shootSpeed":[1500,1500],"hitAudioId":[],"bulletType":[0,100],"attackRange":[500,1000],"qte":[0,0],"duration":[0]},"402":{"id":402,"name":"102大招","weaponType":1,"bulletNum":9999,"chamber":0,"scatterRatio":0.2,"shootDelta":0.25,"singleNum":7,"resPath":"weapon201","hurtRange":30,"isCross":1,"bulletId":33,"showPos":2,"fireAudioId":121,"hitEffectId":0,"fireEffectId":0,"dropId":1002,"sortIndex":0,"hitBack":100,"effectType":3,"warning":0,"unlockWay":[0,0],"hurt":[10,15],"shootSpeed":[2000,2000],"hitAudioId":[],"bulletType":[0,100],"attackRange":[500,1000],"qte":[0,0],"duration":[0]},"403":{"id":403,"name":"103大招","weaponType":1,"bulletNum":8,"chamber":0.8,"scatterRatio":0.3,"shootDelta":0.1,"singleNum":15,"resPath":"weapon111","hurtRange":0,"isCross":1,"bulletId":3,"showPos":2,"fireAudioId":103,"hitEffectId":0,"fireEffectId":0,"dropId":1003,"sortIndex":0,"hitBack":300,"effectType":0,"warning":0,"unlockWay":[0,0],"hurt":[11,15],"shootSpeed":[2500,2800],"hitAudioId":[],"bulletType":[0,100],"attackRange":[500,1000],"qte":[0,0],"duration":[0]},"404":{"id":404,"name":"回旋镖大招","weaponType":2,"bulletNum":9999,"chamber":0,"scatterRatio":0.75,"shootDelta":1,"singleNum":8,"resPath":"weapon104","hurtRange":0,"isCross":1,"bulletId":4,"showPos":2,"fireAudioId":104,"hitEffectId":104,"fireEffectId":0,"dropId":1004,"sortIndex":0,"hitBack":200,"effectType":9,"warning":0,"unlockWay":[0,0],"hurt":[45,75],"shootSpeed":[800,1500,1],"hitAudioId":[205],"bulletType":[1,1080],"attackRange":[500,1000],"qte":[0,0],"duration":[0]},"405":{"id":405,"name":"105大招","weaponType":2,"bulletNum":9999,"chamber":0,"scatterRatio":0.25,"shootDelta":0.1,"singleNum":3,"resPath":"weapon105","hurtRange":0,"isCross":0,"bulletId":34,"showPos":2,"fireAudioId":105,"hitEffectId":110,"fireEffectId":0,"dropId":1005,"sortIndex":0,"hitBack":200,"effectType":2,"warning":0,"unlockWay":[0,0],"hurt":[17,29],"shootSpeed":[2500,2500],"hitAudioId":[],"bulletType":[0,100],"attackRange":[500,1000],"qte":[0,0],"duration":[0]},"406":{"id":406,"name":"106火箭大招","weaponType":1,"bulletNum":9999,"chamber":0,"scatterRatio":0.2,"shootDelta":0.1,"singleNum":1,"resPath":"weapon106","hurtRange":200,"isCross":0,"bulletId":1,"showPos":2,"fireAudioId":106,"hitEffectId":107,"fireEffectId":0,"dropId":1006,"sortIndex":25,"hitBack":100,"effectType":0,"warning":0,"unlockWay":[0,0],"hurt":[45,55],"shootSpeed":[1,4000,1],"hitAudioId":[206],"bulletType":[0,100],"attackRange":[500,1000],"qte":[0,0],"duration":[0]},"407":{"id":407,"name":"黄金ak47测试","weaponType":1,"bulletNum":9999,"chamber":0,"scatterRatio":0.2,"shootDelta":0.1,"singleNum":3,"resPath":"weapon107","hurtRange":0,"isCross":1,"bulletId":8,"showPos":2,"fireAudioId":107,"hitEffectId":106,"fireEffectId":0,"dropId":1007,"sortIndex":26,"hitBack":0,"effectType":0,"warning":0,"unlockWay":[0,0],"hurt":[20,32],"shootSpeed":[2000,4000],"hitAudioId":[],"bulletType":[0,100],"attackRange":[500,1000],"qte":[0,0],"duration":[0]},"409":{"id":409,"name":"109大招","weaponType":4,"bulletNum":9999,"chamber":0,"scatterRatio":1,"shootDelta":0.1,"singleNum":4,"resPath":"weapon120","hurtRange":65,"isCross":1,"bulletId":35,"showPos":2,"fireAudioId":502,"hitEffectId":0,"fireEffectId":0,"dropId":1009,"sortIndex":0,"hitBack":0,"effectType":0,"warning":0,"unlockWay":[0,0],"hurt":[35,55],"shootSpeed":[3000,3000],"hitAudioId":[208],"bulletType":[0,100],"attackRange":[500,1000],"qte":[0,0],"duration":[0]},"411":{"id":411,"name":"111大招","weaponType":1,"bulletNum":9999,"chamber":0,"scatterRatio":0.7,"shootDelta":0.15,"singleNum":8,"resPath":"weapon111","hurtRange":0,"isCross":0,"bulletId":36,"showPos":2,"fireAudioId":111,"hitEffectId":111,"fireEffectId":0,"dropId":1011,"sortIndex":0,"hitBack":200,"effectType":4,"warning":0,"unlockWay":[0,0],"hurt":[15,25],"shootSpeed":[800,2000],"hitAudioId":[],"bulletType":[0,100],"attackRange":[500,1000],"qte":[0,0],"duration":[0]},"412":{"id":412,"name":"112大招","weaponType":2,"bulletNum":9999,"chamber":0,"scatterRatio":0.3,"shootDelta":0.2,"singleNum":4,"resPath":"weapon112","hurtRange":0,"isCross":1,"bulletId":12,"showPos":2,"fireAudioId":112,"hitEffectId":112,"fireEffectId":0,"dropId":1012,"sortIndex":0,"hitBack":500,"effectType":6,"warning":0,"unlockWay":[0,0],"hurt":[30,50],"shootSpeed":[2800,2800],"hitAudioId":[],"bulletType":[0,500],"attackRange":[500,1000],"qte":[0,0],"duration":[0]},"417":{"id":417,"name":"117大招","weaponType":1,"bulletNum":9999,"chamber":0,"scatterRatio":0,"shootDelta":1,"singleNum":1,"resPath":"weapon117","hurtRange":480,"isCross":0,"bulletId":37,"showPos":2,"fireAudioId":117,"hitEffectId":117,"fireEffectId":0,"dropId":1017,"sortIndex":0,"hitBack":400,"effectType":0,"warning":0,"unlockWay":[0,0],"hurt":[135,225],"shootSpeed":[1300,1300],"hitAudioId":[3001],"bulletType":[0,100],"attackRange":[500,1000],"qte":[0,0],"duration":[0]},"420":{"id":420,"name":"120大招","weaponType":5,"bulletNum":9999,"chamber":0,"scatterRatio":1.57,"shootDelta":0.1,"singleNum":4,"resPath":"weapon120","hurtRange":65,"isCross":1,"bulletId":20,"showPos":2,"fireAudioId":0,"hitEffectId":0,"fireEffectId":0,"dropId":1020,"sortIndex":0,"hitBack":200,"effectType":5,"warning":0,"unlockWay":[0,0],"hurt":[45,75],"shootSpeed":[3000,3000],"hitAudioId":[208],"bulletType":[2,120],"attackRange":[500,1000],"qte":[0,0],"duration":[0]},"421":{"id":421,"name":"121大招","weaponType":2,"bulletNum":9999,"chamber":0,"scatterRatio":5,"shootDelta":0.4,"singleNum":1,"resPath":"weapon121","hurtRange":0,"isCross":1,"bulletId":38,"showPos":2,"fireAudioId":123,"hitEffectId":421,"fireEffectId":0,"dropId":1021,"sortIndex":0,"hitBack":200,"effectType":7,"warning":0,"unlockWay":[0,0],"hurt":[68,113],"shootSpeed":[1000,1000],"hitAudioId":[210],"bulletType":[0,100],"attackRange":[500,1000],"qte":[0,0],"duration":[0]},"422":{"id":422,"name":"122大招","weaponType":2,"bulletNum":9999,"chamber":0,"scatterRatio":0.1,"shootDelta":1,"singleNum":1,"resPath":"weapon122","hurtRange":0,"isCross":1,"bulletId":39,"showPos":2,"fireAudioId":124,"hitEffectId":0,"fireEffectId":0,"dropId":1022,"sortIndex":0,"hitBack":0,"effectType":8,"warning":0,"unlockWay":[0,0],"hurt":[90,150],"shootSpeed":[100,2000,1],"hitAudioId":[209],"bulletType":[0,100],"attackRange":[500,1000],"qte":[0,0],"duration":[0]},"501":{"id":501,"name":"小蝙蝠远程攻击","weaponType":2,"bulletNum":9999,"chamber":0,"scatterRatio":0.05,"shootDelta":5,"singleNum":10,"resPath":"weapon305","hurtRange":0,"isCross":0,"bulletId":43,"showPos":2,"fireAudioId":0,"hitEffectId":0,"fireEffectId":0,"dropId":5001,"sortIndex":0,"hitBack":0,"effectType":0,"warning":0,"unlockWay":[0,0],"hurt":[35,35],"shootSpeed":[300,300],"hitAudioId":[],"bulletType":[0,100],"attackRange":[1000,1000],"qte":[0,0],"duration":[0]},"502":{"id":502,"name":"小仙人球攻击","weaponType":2,"bulletNum":3,"chamber":3,"scatterRatio":0,"shootDelta":0.5,"singleNum":1,"resPath":"weapon305","hurtRange":0,"isCross":0,"bulletId":44,"showPos":2,"fireAudioId":0,"hitEffectId":0,"fireEffectId":0,"dropId":5001,"sortIndex":0,"hitBack":0,"effectType":0,"warning":0,"unlockWay":[0,0],"hurt":[35,35],"shootSpeed":[350,350],"hitAudioId":[],"bulletType":[0,100],"attackRange":[1000,1000],"qte":[0,0],"duration":[0]},"503":{"id":503,"name":"小蝙蝠远程攻击","weaponType":2,"bulletNum":25,"chamber":5,"scatterRatio":0,"shootDelta":0.25,"singleNum":1,"resPath":"weapon305","hurtRange":0,"isCross":0,"bulletId":43,"showPos":2,"fireAudioId":0,"hitEffectId":0,"fireEffectId":0,"dropId":5001,"sortIndex":0,"hitBack":0,"effectType":0,"warning":0,"unlockWay":[0,0],"hurt":[35,35],"shootSpeed":[300,300],"hitAudioId":[],"bulletType":[3,-100],"attackRange":[1000,1000],"qte":[0,0],"duration":[0]},"505":{"id":505,"name":"怪物猫的旋转攻击","weaponType":2,"bulletNum":99,"chamber":0,"scatterRatio":0,"shootDelta":2.5,"singleNum":1,"resPath":"weapon305","hurtRange":0,"isCross":0,"bulletId":6,"showPos":2,"fireAudioId":0,"hitEffectId":0,"fireEffectId":0,"dropId":3005,"sortIndex":0,"hitBack":0,"effectType":0,"warning":0,"unlockWay":[0,0],"hurt":[50,50],"shootSpeed":[300,300],"hitAudioId":[],"bulletType":[1,250],"attackRange":[1000,1000],"qte":[0,0],"duration":[0]},"506":{"id":506,"name":"怪物鹰的攻击","weaponType":2,"bulletNum":99,"chamber":0,"scatterRatio":0.2,"shootDelta":3,"singleNum":3,"resPath":"weapon306","hurtRange":0,"isCross":0,"bulletId":7,"showPos":2,"fireAudioId":0,"hitEffectId":0,"fireEffectId":0,"dropId":3006,"sortIndex":0,"hitBack":0,"effectType":0,"warning":0,"unlockWay":[0,0],"hurt":[50,50],"shootSpeed":[400,400],"hitAudioId":[],"bulletType":[0,100],"attackRange":[1000,1000],"qte":[0,0],"duration":[0]},"601":{"id":601,"name":"冲刺怪物","weaponType":1,"bulletNum":9999,"chamber":0,"scatterRatio":0,"shootDelta":2,"singleNum":0,"resPath":"weapon102","hurtRange":0,"isCross":0,"bulletId":2,"showPos":2,"fireAudioId":102,"hitEffectId":105,"fireEffectId":0,"dropId":1002,"sortIndex":9,"hitBack":0,"effectType":3,"warning":0.8,"unlockWay":[0,0],"hurt":[50,50],"shootSpeed":[1500,2500],"hitAudioId":[],"bulletType":[0,100],"attackRange":[500,1000],"qte":[0,0],"duration":[0,0]},"605":{"id":605,"name":"树-三连发-绿叶5","weaponType":2,"bulletNum":99999999,"chamber":0,"scatterRatio":0.3,"shootDelta":1.5,"singleNum":3,"resPath":"weapon301","hurtRange":0,"isCross":0,"bulletId":27,"showPos":2,"fireAudioId":0,"hitEffectId":0,"fireEffectId":0,"dropId":1001,"sortIndex":0,"hitBack":0,"effectType":0,"warning":0,"unlockWay":[0,0],"hurt":[50,50],"shootSpeed":[500,500],"hitAudioId":[],"bulletType":[0,100],"attackRange":[500,1000],"qte":[0,0],"duration":[0]},"606":{"id":606,"name":"四脚石头-螺旋子弹10","weaponType":2,"bulletNum":35,"chamber":1.5,"scatterRatio":0,"shootDelta":0.1,"singleNum":1,"resPath":"weapon301","hurtRange":0,"isCross":0,"bulletId":28,"showPos":2,"fireAudioId":0,"hitEffectId":0,"fireEffectId":0,"dropId":1001,"sortIndex":0,"hitBack":0,"effectType":0,"warning":0,"unlockWay":[0,0],"hurt":[50,50],"shootSpeed":[350,350],"hitAudioId":[],"bulletType":[3,360],"attackRange":[500,1000],"qte":[0,0],"duration":[0]},"607":{"id":607,"name":"机器人16激光15","weaponType":2,"bulletNum":99999999,"chamber":0,"scatterRatio":0.4,"shootDelta":2,"singleNum":16,"resPath":"weapon301","hurtRange":0,"isCross":1,"bulletId":45,"showPos":2,"fireAudioId":0,"hitEffectId":0,"fireEffectId":0,"dropId":1001,"sortIndex":0,"hitBack":0,"effectType":0,"warning":1.2,"unlockWay":[0,0],"hurt":[50,50],"shootSpeed":[3000,3000],"hitAudioId":[],"bulletType":[0,100],"attackRange":[500,1000],"qte":[0,0],"duration":[0]},"608":{"id":608,"name":"蝙蝠-圆环子弹-紫色20","weaponType":2,"bulletNum":3,"chamber":2,"scatterRatio":0.39,"shootDelta":1,"singleNum":16,"resPath":"weapon301","hurtRange":0,"isCross":0,"bulletId":27,"showPos":2,"fireAudioId":0,"hitEffectId":0,"fireEffectId":0,"dropId":1001,"sortIndex":0,"hitBack":0,"effectType":0,"warning":0,"unlockWay":[0,0],"hurt":[50,50],"shootSpeed":[500,500],"hitAudioId":[],"bulletType":[0,100],"attackRange":[500,1000],"qte":[0,0],"duration":[0]},"609":{"id":609,"name":"四脚石头25","weaponType":2,"bulletNum":30,"chamber":2,"scatterRatio":3.14,"shootDelta":0.15,"singleNum":2,"resPath":"weapon301","hurtRange":0,"isCross":0,"bulletId":28,"showPos":2,"fireAudioId":0,"hitEffectId":0,"fireEffectId":0,"dropId":1001,"sortIndex":0,"hitBack":0,"effectType":0,"warning":0,"unlockWay":[0,0],"hurt":[50,50],"shootSpeed":[500,500],"hitAudioId":[],"bulletType":[3,90],"attackRange":[500,1000],"qte":[0,0],"duration":[0]},"610":{"id":610,"name":"喷火龙火柱30","weaponType":2,"bulletNum":30,"chamber":2,"scatterRatio":0,"shootDelta":0.1,"singleNum":1,"resPath":"weapon111","hurtRange":0,"isCross":0,"bulletId":40,"showPos":2,"fireAudioId":111,"hitEffectId":111,"fireEffectId":0,"dropId":1011,"sortIndex":0,"hitBack":0,"effectType":4,"warning":0,"unlockWay":[0,0],"hurt":[50,50],"shootSpeed":[450,450],"hitAudioId":[],"bulletType":[1,250],"attackRange":[500,1000],"qte":[0,0],"duration":[0]}}]],0,0,[],[],[]]