[1,0,0,[["cc.JsonAsset",["_name","json"],1]],[[0,0,1,3]],[[0,"Barrier",{"1":{"id":1,"firstDropId":2001,"normalDropId":5001,"monCapaticy":1,"bronRule":[[[102,5,103,10],2,1]],"attackExp":[100,100],"eventID":[]},"2":{"id":2,"normalDropId":5001,"monCapaticy":1,"bronRule":[[[104,5,105,5,106,10,107,1],3,1]],"attackExp":[100,100],"eventID":[1]},"3":{"id":3,"normalDropId":5001,"monCapaticy":1,"bronRule":[[[101,15,104,5,108,2,109,1,107,2],3,1,2]],"attackExp":[100,100],"eventID":[]},"4":{"id":4,"normalDropId":5001,"monCapaticy":1,"bronRule":[[[110,5,106,10,104,5,112,1,604,1],3,1,2,3]],"attackExp":[50,50],"eventID":[]},"5":{"id":5,"firstDropId":2002,"normalDropId":5001,"monCapaticy":1,"bronRule":[[[331,1],1,1]],"attackExp":[50,50],"eventID":[]},"6":{"id":6,"normalDropId":5001,"monCapaticy":1,"bronRule":[[[110,20,113,2,109,1],3]],"attackExp":[50,50],"eventID":[]},"7":{"id":7,"normalDropId":5001,"monCapaticy":1,"bronRule":[[[105,10,103,20,107,6,114,1],3]],"attackExp":[50,50],"eventID":[2,3]},"8":{"id":8,"normalDropId":5001,"monCapaticy":1,"bronRule":[[[102,30,115,1,112,1,119,1],2]],"attackExp":[50,50],"eventID":[]},"9":{"id":9,"normalDropId":5001,"monCapaticy":1,"bronRule":[[[116,20,104,10,117,2,118,1,109,1,117,3,604,1],3]],"attackExp":[50,50],"eventID":[]},"10":{"id":10,"firstDropId":2003,"normalDropId":5001,"monCapaticy":1.195,"bronRule":[[[332,1],1,1]],"attackExp":[50,50],"eventID":[]},"11":{"id":11,"normalDropId":5001,"monCapaticy":1.2189,"bronRule":[[[611,4,235,20],3]],"attackExp":[50,50],"eventID":[]},"12":{"id":12,"normalDropId":5001,"monCapaticy":1.2433,"bronRule":[[[201,40,328,12,611,4,330,1],3]],"attackExp":[50,50],"eventID":[4]},"13":{"id":13,"normalDropId":5001,"monCapaticy":1.2682,"bronRule":[[[309,20,324,4,611,2,302,1],3]],"attackExp":[50,50],"eventID":[]},"14":{"id":14,"normalDropId":5001,"monCapaticy":1.2936,"bronRule":[[[231,40,325,10,611,3,312,2,604,1],3]],"attackExp":[50,50],"eventID":[]},"15":{"id":15,"firstDropId":2004,"normalDropId":5001,"monCapaticy":1.3195,"bronRule":[[[333,1],1,1]],"attackExp":[50,50],"eventID":[]},"16":{"id":16,"normalDropId":5001,"monCapaticy":1.3459,"bronRule":[[[316,30,308,30,318,10,328,10,326,10],3]],"attackExp":[50,50],"eventID":[]},"17":{"id":17,"normalDropId":5001,"monCapaticy":1.3728,"bronRule":[[[308,30,319,30,318,10,325,15,607,5],3]],"attackExp":[50,50],"eventID":[5]},"18":{"id":18,"normalDropId":5001,"monCapaticy":1.4003,"bronRule":[[[319,50,624,2,602,5,329,5],3]],"attackExp":[10,10],"eventID":[]},"19":{"id":19,"normalDropId":5001,"monCapaticy":1.4283,"bronRule":[[[320,30,303,30,311,10,611,5,624,5,327,5,604,1],3]],"attackExp":[10,10],"eventID":[]},"20":{"id":20,"firstDropId":2005,"normalDropId":5001,"monCapaticy":1.4569,"bronRule":[[[334,1],1,1]],"attackExp":[10,10],"eventID":[]},"21":{"id":21,"firstDropId":2006,"normalDropId":5002,"monCapaticy":1.5,"bronRule":[[[303,10,301,10,318,3,329,3],3]],"attackExp":[100,100],"eventID":[]},"22":{"id":22,"normalDropId":5002,"monCapaticy":1.545,"bronRule":[[[301,10,317,10,318,5,328,2,311,1],3]],"attackExp":[50,50],"eventID":[6]},"23":{"id":23,"normalDropId":5002,"monCapaticy":1.5914,"bronRule":[[[317,20,305,5,318,5,607,1,324,1,325,3],3]],"attackExp":[50,50],"eventID":[]},"24":{"id":24,"normalDropId":5002,"monCapaticy":1.6391,"bronRule":[[[305,20,313,10,327,5,606,1,604,1],3]],"attackExp":[50,50],"eventID":[]},"25":{"id":25,"normalDropId":5002,"monCapaticy":1.6883,"bronRule":[[[335,1],1,1]],"attackExp":[50,50],"eventID":[]},"26":{"id":26,"normalDropId":5002,"monCapaticy":1.7389,"bronRule":[[[313,30,314,10,318,5,311,5,329,5,607,2],3]],"attackExp":[50,50],"eventID":[]},"27":{"id":27,"normalDropId":5002,"monCapaticy":1.7911,"bronRule":[[[314,30,315,5,318,5,601,2,328,10,325,10],3]],"attackExp":[50,50],"eventID":[7]},"28":{"id":28,"normalDropId":5002,"monCapaticy":1.8448,"bronRule":[[[315,30,309,10,318,5,606,2,324,5,327,5],3]],"attackExp":[50,50],"eventID":[]},"29":{"id":29,"normalDropId":5002,"monCapaticy":1.9001,"bronRule":[[[309,20,308,30,318,10,606,2,328,10,604,1],3]],"attackExp":[50,50],"eventID":[]},"30":{"id":30,"firstDropId":2007,"normalDropId":5002,"monCapaticy":1.9571,"bronRule":[[[339,1],1,1]],"attackExp":[34,34],"eventID":[]},"31":{"id":31,"normalDropId":5002,"monCapaticy":2.0158,"bronRule":[[[319,30,318,10,325,30,624,2,324,10,302,1],2]],"attackExp":[34,34],"eventID":[]},"32":{"id":32,"normalDropId":5002,"monCapaticy":2.0763,"bronRule":[[[308,30,605,30,318,30,606,2,602,2],2]],"attackExp":[34,34],"eventID":[8,9]},"33":{"id":33,"normalDropId":5002,"monCapaticy":2.1386,"bronRule":[[[305,40,311,10,624,2,318,10,330,1],2]],"attackExp":[34,34],"eventID":[]},"34":{"id":34,"normalDropId":5002,"monCapaticy":2.2028,"bronRule":[[[326,30,319,30,601,5,602,5,604,1],2]],"attackExp":[34,34],"eventID":[]},"35":{"id":35,"firstDropId":2008,"normalDropId":5002,"monCapaticy":2.2689,"bronRule":[[[340,1],1,1]],"attackExp":[34,34],"eventID":[]},"36":{"id":36,"normalDropId":5002,"monCapaticy":2.337,"bronRule":[[[309,30,318,5,311,5],3]],"attackExp":[34,34],"eventID":[]},"37":{"id":37,"normalDropId":5002,"monCapaticy":2.4071,"bronRule":[[[308,30,605,30,318,10,602,2],3]],"attackExp":[34,34],"eventID":[10,11]},"38":{"id":38,"normalDropId":5002,"monCapaticy":2.4793,"bronRule":[[[309,20,324,6,611,4,302,1],3]],"attackExp":[34,34],"eventID":[]},"39":{"id":39,"normalDropId":5002,"monCapaticy":2.5537,"bronRule":[[[231,40,325,10,611,6,312,2,604,1],3]],"attackExp":[34,34],"eventID":[]},"40":{"id":40,"firstDropId":2009,"normalDropId":5002,"monCapaticy":2.6303,"bronRule":[[[341,1],1,1]],"attackExp":[34,34],"eventID":[]},"41":{"id":41,"normalDropId":5002,"monCapaticy":2.7092,"bronRule":[[[316,30,308,30,318,10,328,10,326,10],3]],"attackExp":[34,34],"eventID":[]},"42":{"id":42,"normalDropId":5002,"monCapaticy":2.7905,"bronRule":[[[308,30,319,30,318,10,325,15,607,5],3]],"attackExp":[34,34],"eventID":[12,13]},"43":{"id":43,"normalDropId":5002,"monCapaticy":2.8742,"bronRule":[[[319,30,320,30,624,5,324,5,602,5,329,5],3]],"attackExp":[34,34],"eventID":[]},"44":{"id":44,"normalDropId":5002,"monCapaticy":2.9604,"bronRule":[[[320,30,303,30,311,10,611,5,624,5,327,5,604,1],3]],"attackExp":[34,34],"eventID":[]},"45":{"id":45,"firstDropId":2010,"normalDropId":5002,"monCapaticy":3.0492,"bronRule":[[[341,1],1,1]],"attackExp":[10,10],"eventID":[]},"46":{"id":46,"normalDropId":5002,"monCapaticy":3.1407,"bronRule":[[[303,30,301,30,318,10,328,10,606,5],3]],"attackExp":[10,10],"eventID":[]},"47":{"id":47,"normalDropId":5002,"monCapaticy":3.2349,"bronRule":[[[301,30,317,30,318,5,601,5,329,5,607,5],3]],"attackExp":[10,10],"eventID":[14]},"48":{"id":48,"normalDropId":5002,"monCapaticy":3.3319,"bronRule":[[[317,30,305,30,318,5,607,5,624,5,325,10],3]],"attackExp":[10,10],"eventID":[]},"49":{"id":49,"normalDropId":5002,"monCapaticy":3.4319,"bronRule":[[[305,30,313,30,327,5,602,5,606,5,604,1],3]],"attackExp":[10,10],"eventID":[]},"50":{"id":50,"normalDropId":5003,"monCapaticy":3.5349,"bronRule":[[[341,1],1,1]],"attackExp":[10,10],"eventID":[]},"51":{"id":51,"firstDropId":2020,"normalDropId":5003,"monCapaticy":4,"bronRule":[[[303,10,318,3,329,3],2]],"attackExp":[100,100],"eventID":[]},"52":{"id":52,"normalDropId":5003,"monCapaticy":4.12,"bronRule":[[[301,10,318,5,328,2],2]],"attackExp":[50,50],"eventID":[15]},"53":{"id":53,"normalDropId":5003,"monCapaticy":4.2436,"bronRule":[[[317,10,318,5,311,1,325,3],2]],"attackExp":[50,50],"eventID":[]},"54":{"id":54,"normalDropId":5003,"monCapaticy":4.3709,"bronRule":[[[305,10,327,5,606,1,604,1],2]],"attackExp":[50,50],"eventID":[]},"55":{"id":55,"normalDropId":5003,"monCapaticy":4.502,"bronRule":[[[335,1],1,1]],"attackExp":[50,50],"eventID":[]},"56":{"id":56,"normalDropId":5003,"monCapaticy":4.6371,"bronRule":[[[313,5,318,5,311,5,329,5,607,2],2]],"attackExp":[20,20],"eventID":[]},"57":{"id":57,"normalDropId":5003,"monCapaticy":4.7762,"bronRule":[[[314,10,318,5,601,2,328,10,325,10],2]],"attackExp":[20,20],"eventID":[16]},"58":{"id":58,"normalDropId":5003,"monCapaticy":4.9195,"bronRule":[[[315,20,318,5,606,2,324,5,327,5],2]],"attackExp":[20,20],"eventID":[]},"59":{"id":59,"normalDropId":5003,"monCapaticy":5.0671,"bronRule":[[[309,20,318,10,606,2,328,10,604,1],2]],"attackExp":[20,20],"eventID":[]},"60":{"id":60,"normalDropId":5003,"monCapaticy":5.2191,"bronRule":[[[339,1],1,1]],"attackExp":[20,20],"eventID":[]},"61":{"id":61,"normalDropId":5003,"monCapaticy":5.3757,"bronRule":[[[319,15,318,10,325,30,624,2,324,3,302,1],2]],"attackExp":[20,20],"eventID":[]},"62":{"id":62,"normalDropId":5003,"monCapaticy":5.537,"bronRule":[[[308,15,605,30,318,30,606,4],2]],"attackExp":[20,20],"eventID":[17]},"63":{"id":63,"normalDropId":5003,"monCapaticy":5.7031,"bronRule":[[[305,15,311,10,624,2,318,10,330,1],2]],"attackExp":[20,20],"eventID":[]},"64":{"id":64,"normalDropId":5003,"monCapaticy":5.8742,"bronRule":[[[326,30,601,5,604,1],2]],"attackExp":[20,20],"eventID":[]},"65":{"id":65,"normalDropId":5003,"monCapaticy":6.0504,"bronRule":[[[340,1],1,1]],"attackExp":[20,20],"eventID":[]},"66":{"id":66,"normalDropId":5003,"monCapaticy":6.2319,"bronRule":[[[309,30,318,5,311,5],2]],"attackExp":[20,20],"eventID":[]},"67":{"id":67,"normalDropId":5003,"monCapaticy":6.4189,"bronRule":[[[308,30,605,30,318,10,602,2],2]],"attackExp":[20,20],"eventID":[18]},"68":{"id":68,"normalDropId":5003,"monCapaticy":6.6115,"bronRule":[[[309,20,324,2,611,4,302,1],2]],"attackExp":[20,20],"eventID":[]},"69":{"id":69,"normalDropId":5003,"monCapaticy":6.8098,"bronRule":[[[231,20,325,10,611,6,312,2,604,1],2]],"attackExp":[20,20],"eventID":[]},"70":{"id":70,"normalDropId":5003,"monCapaticy":7.0141,"bronRule":[[[341,1],1,1]],"attackExp":[20,20],"eventID":[]},"71":{"id":71,"normalDropId":5003,"monCapaticy":7.2245,"bronRule":[[[316,30,318,10,328,10,326,10],3]],"attackExp":[20,20],"eventID":[]},"72":{"id":72,"normalDropId":5003,"monCapaticy":7.4412,"bronRule":[[[308,30,318,10,325,15,607,3],3]],"attackExp":[20,20],"eventID":[19]},"73":{"id":73,"normalDropId":5003,"monCapaticy":7.6644,"bronRule":[[[319,30,624,5,602,5,329,5],3]],"attackExp":[20,20],"eventID":[]},"74":{"id":74,"normalDropId":5003,"monCapaticy":7.8943,"bronRule":[[[320,30,311,10,611,5,624,5,327,5,604,1],3]],"attackExp":[20,20],"eventID":[]},"75":{"id":75,"normalDropId":5003,"monCapaticy":8.1311,"bronRule":[[[342,1],1,1]],"attackExp":[20,20],"eventID":[]},"76":{"id":76,"normalDropId":5003,"monCapaticy":8.375,"bronRule":[[[303,30,301,30,318,10,328,10,606,5],3]],"attackExp":[20,20],"eventID":[]},"77":{"id":77,"normalDropId":5003,"monCapaticy":8.6263,"bronRule":[[[301,30,317,30,318,5,601,5,329,5,607,5],3]],"attackExp":[20,20],"eventID":[20]},"78":{"id":78,"normalDropId":5003,"monCapaticy":8.8851,"bronRule":[[[317,30,305,30,318,5,607,5,624,5,325,10],3]],"attackExp":[20,20],"eventID":[]},"79":{"id":79,"normalDropId":5003,"monCapaticy":9.1517,"bronRule":[[[305,30,313,30,327,5,602,5,606,5,604,1],3]],"attackExp":[20,20],"eventID":[]},"80":{"id":80,"normalDropId":5003,"monCapaticy":9.4263,"bronRule":[[[343,1],1,1]],"attackExp":[20,20],"eventID":[]},"81":{"id":81,"normalDropId":5003,"monCapaticy":9.7091,"bronRule":[[[305,40,611,4,235,40],3]],"attackExp":[20,20],"eventID":[]},"82":{"id":82,"normalDropId":5003,"monCapaticy":10.0004,"bronRule":[[[201,40,328,12,611,4,330,1],3]],"attackExp":[20,20],"eventID":[21]},"83":{"id":83,"normalDropId":5003,"monCapaticy":10.3004,"bronRule":[[[309,20,324,6,611,4,302,1],3]],"attackExp":[20,20],"eventID":[]},"84":{"id":84,"normalDropId":5003,"monCapaticy":10.6094,"bronRule":[[[231,40,325,10,611,6,312,2,604,1],3]],"attackExp":[20,20],"eventID":[]},"85":{"id":85,"normalDropId":5003,"monCapaticy":10.9277,"bronRule":[[[333,1],1,1]],"attackExp":[20,20],"eventID":[]},"86":{"id":86,"normalDropId":5003,"monCapaticy":11.2555,"bronRule":[[[316,30,308,30,318,10,328,10,326,10],3]],"attackExp":[20,20],"eventID":[]},"87":{"id":87,"normalDropId":5003,"monCapaticy":11.5932,"bronRule":[[[308,30,319,30,318,10,325,15,607,5],3]],"attackExp":[20,20],"eventID":[22]},"88":{"id":88,"normalDropId":5003,"monCapaticy":11.941,"bronRule":[[[319,60,624,2,324,10,602,5,329,5],3]],"attackExp":[20,20],"eventID":[]},"89":{"id":89,"normalDropId":5003,"monCapaticy":12.2992,"bronRule":[[[320,30,303,30,311,10,611,5,624,5,327,5,604,1],3]],"attackExp":[20,20],"eventID":[]},"90":{"id":90,"normalDropId":5003,"monCapaticy":12.6682,"bronRule":[[[334,1],1,1]],"attackExp":[20,20],"eventID":[]},"91":{"id":91,"normalDropId":5003,"monCapaticy":13.0482,"bronRule":[[[316,30,319,30,318,5,325,30,624,10,324,10,302,1],2]],"attackExp":[10,10],"eventID":[]},"92":{"id":92,"normalDropId":5003,"monCapaticy":13.4396,"bronRule":[[[308,60,605,30,318,30,606,5],2]],"attackExp":[10,10],"eventID":[15,16,17,18]},"93":{"id":93,"normalDropId":5003,"monCapaticy":13.8428,"bronRule":[[[305,60,311,30,624,10,318,10,330,1],2]],"attackExp":[10,10],"eventID":[]},"94":{"id":94,"normalDropId":5003,"monCapaticy":14.2581,"bronRule":[[[326,30,309,30,601,10,602,10,604,1],2]],"attackExp":[10,10],"eventID":[]},"95":{"id":95,"normalDropId":5003,"monCapaticy":14.6858,"bronRule":[[[344,1],1,1]],"attackExp":[10,10],"eventID":[]},"96":{"id":96,"normalDropId":5003,"monCapaticy":15.1264,"bronRule":[[[313,30,314,30,318,5,311,10,329,5,607,5],3]],"attackExp":[10,10],"eventID":[]},"97":{"id":97,"normalDropId":5003,"monCapaticy":15.5802,"bronRule":[[[314,30,315,30,318,5,601,5,328,10,325,10],3]],"attackExp":[10,10],"eventID":[19,20,21,22]},"98":{"id":98,"normalDropId":5003,"monCapaticy":16.0476,"bronRule":[[[315,30,309,30,318,5,606,5,324,10,327,5],3]],"attackExp":[10,10],"eventID":[]},"99":{"id":99,"normalDropId":5003,"monCapaticy":16.529,"bronRule":[[[309,30,308,30,318,5,606,10,328,10,604,1],3]],"attackExp":[10,10],"eventID":[]},"100":{"id":100,"normalDropId":5004,"monCapaticy":17.0249,"bronRule":[[[345,1],1,1]],"attackExp":[10,10],"eventID":[]},"101":{"id":101,"normalDropId":5004,"monCapaticy":15,"bronRule":[[[303,10,301,10,318,3,329,3],3]],"attackExp":[100,100],"eventID":[]},"102":{"id":102,"normalDropId":5004,"monCapaticy":15.45,"bronRule":[[[301,10,317,10,318,5,328,2,311,1],3]],"attackExp":[50,50],"eventID":[]},"103":{"id":103,"normalDropId":5004,"monCapaticy":15.9135,"bronRule":[[[317,20,305,5,318,5,607,1,324,1,325,3],3]],"attackExp":[50,50],"eventID":[]},"104":{"id":104,"normalDropId":5004,"monCapaticy":16.3909,"bronRule":[[[305,20,313,10,327,5,606,1,604,1],3]],"attackExp":[50,50],"eventID":[]},"105":{"id":105,"normalDropId":5004,"monCapaticy":16.8826,"bronRule":[[[335,1],1,1]],"attackExp":[50,50],"eventID":[]},"106":{"id":106,"normalDropId":5004,"monCapaticy":17.3891,"bronRule":[[[313,30,314,10,318,5,311,5,329,5,607,2],3]],"attackExp":[20,20],"eventID":[]},"107":{"id":107,"normalDropId":5004,"monCapaticy":17.9108,"bronRule":[[[314,30,315,5,318,5,601,2,328,10,325,10],3]],"attackExp":[20,20],"eventID":[]},"108":{"id":108,"normalDropId":5004,"monCapaticy":18.4481,"bronRule":[[[315,30,309,10,318,5,606,2,324,5,327,5],3]],"attackExp":[20,20],"eventID":[]},"109":{"id":109,"normalDropId":5004,"monCapaticy":19.0015,"bronRule":[[[309,20,308,30,318,10,606,2,328,10,604,1],3]],"attackExp":[20,20],"eventID":[]},"110":{"id":110,"normalDropId":5004,"monCapaticy":19.5715,"bronRule":[[[339,1],1,1]],"attackExp":[20,20],"eventID":[]},"111":{"id":111,"normalDropId":5004,"monCapaticy":20.1586,"bronRule":[[[319,30,318,10,325,30,624,2,324,10,302,1],2]],"attackExp":[20,20],"eventID":[]},"112":{"id":112,"normalDropId":5004,"monCapaticy":20.7634,"bronRule":[[[308,30,605,30,318,30,606,2,602,2],2]],"attackExp":[20,20],"eventID":[]},"113":{"id":113,"normalDropId":5004,"monCapaticy":21.3863,"bronRule":[[[305,40,311,10,624,2,318,10,330,1],2]],"attackExp":[20,20],"eventID":[]},"114":{"id":114,"normalDropId":5004,"monCapaticy":22.0279,"bronRule":[[[326,30,319,30,601,5,602,5,604,1],2]],"attackExp":[20,20],"eventID":[]},"115":{"id":115,"normalDropId":5004,"monCapaticy":22.6887,"bronRule":[[[340,1],1,1]],"attackExp":[20,20],"eventID":[]},"116":{"id":116,"normalDropId":5004,"monCapaticy":23.3694,"bronRule":[[[309,30,318,5,311,5],3]],"attackExp":[20,20],"eventID":[]},"117":{"id":117,"normalDropId":5004,"monCapaticy":24.0705,"bronRule":[[[308,30,605,30,318,10,602,2],3]],"attackExp":[20,20],"eventID":[]},"118":{"id":118,"normalDropId":5004,"monCapaticy":24.7926,"bronRule":[[[309,20,324,6,611,4,302,1],3]],"attackExp":[20,20],"eventID":[]},"119":{"id":119,"normalDropId":5004,"monCapaticy":25.5364,"bronRule":[[[231,40,325,10,611,6,312,2,604,1],3]],"attackExp":[20,20],"eventID":[]},"120":{"id":120,"normalDropId":5004,"monCapaticy":26.3025,"bronRule":[[[341,1],1,1]],"attackExp":[20,20],"eventID":[]},"121":{"id":121,"normalDropId":5004,"monCapaticy":27.0916,"bronRule":[[[316,30,308,30,318,10,328,10,326,10],3]],"attackExp":[20,20],"eventID":[]},"122":{"id":122,"normalDropId":5004,"monCapaticy":27.9043,"bronRule":[[[308,30,319,30,318,10,325,15,607,5],3]],"attackExp":[20,20],"eventID":[]},"123":{"id":123,"normalDropId":5004,"monCapaticy":28.7414,"bronRule":[[[319,30,320,30,624,5,324,5,602,5,329,5],3]],"attackExp":[20,20],"eventID":[]},"124":{"id":124,"normalDropId":5004,"monCapaticy":29.6036,"bronRule":[[[320,30,303,30,311,10,611,5,624,5,327,5,604,1],3]],"attackExp":[20,20],"eventID":[]},"125":{"id":125,"normalDropId":5004,"monCapaticy":30.4917,"bronRule":[[[342,1],1,1]],"attackExp":[20,20],"eventID":[]},"126":{"id":126,"normalDropId":5004,"monCapaticy":31.4065,"bronRule":[[[303,30,301,30,318,10,328,10,606,5],3]],"attackExp":[20,20],"eventID":[]},"127":{"id":127,"normalDropId":5004,"monCapaticy":32.3487,"bronRule":[[[301,30,317,30,318,5,601,5,329,5,607,5],3]],"attackExp":[20,20],"eventID":[]},"128":{"id":128,"normalDropId":5004,"monCapaticy":33.3192,"bronRule":[[[317,30,305,30,318,5,607,5,624,5,325,10],3]],"attackExp":[20,20],"eventID":[]},"129":{"id":129,"normalDropId":5004,"monCapaticy":34.3188,"bronRule":[[[305,30,313,30,327,5,602,5,606,5,604,1],3]],"attackExp":[20,20],"eventID":[]},"130":{"id":130,"normalDropId":5004,"monCapaticy":35.3484,"bronRule":[[[343,1],1,1]],"attackExp":[20,20],"eventID":[]},"131":{"id":131,"normalDropId":5004,"monCapaticy":36.4089,"bronRule":[[[305,40,611,4,235,40],3]],"attackExp":[20,20],"eventID":[]},"132":{"id":132,"normalDropId":5004,"monCapaticy":37.5012,"bronRule":[[[201,40,328,12,611,4,330,1],3]],"attackExp":[20,20],"eventID":[]},"133":{"id":133,"normalDropId":5004,"monCapaticy":38.6262,"bronRule":[[[309,20,324,6,611,4,302,1],3]],"attackExp":[20,20],"eventID":[]},"134":{"id":134,"normalDropId":5004,"monCapaticy":39.785,"bronRule":[[[231,40,325,10,611,6,312,2,604,1],3]],"attackExp":[20,20],"eventID":[]},"135":{"id":135,"normalDropId":5004,"monCapaticy":40.9786,"bronRule":[[[333,1],1,1]],"attackExp":[20,20],"eventID":[]},"136":{"id":136,"normalDropId":5004,"monCapaticy":42.208,"bronRule":[[[316,30,308,30,318,10,328,10,326,10],3]],"attackExp":[20,20],"eventID":[]},"137":{"id":137,"normalDropId":5004,"monCapaticy":43.4742,"bronRule":[[[308,30,319,30,318,10,325,15,607,5],3]],"attackExp":[20,20],"eventID":[]},"138":{"id":138,"normalDropId":5004,"monCapaticy":44.7784,"bronRule":[[[319,60,624,2,324,10,602,5,329,5],3]],"attackExp":[20,20],"eventID":[]},"139":{"id":139,"normalDropId":5004,"monCapaticy":46.1218,"bronRule":[[[320,30,303,30,311,10,611,5,624,5,327,5,604,1],3]],"attackExp":[20,20],"eventID":[]},"140":{"id":140,"normalDropId":5004,"monCapaticy":47.5055,"bronRule":[[[334,1],1,1]],"attackExp":[20,20],"eventID":[]},"141":{"id":141,"normalDropId":5004,"monCapaticy":48.9307,"bronRule":[[[316,30,319,30,318,5,325,30,624,10,324,10,302,1],2]],"attackExp":[10,10],"eventID":[]},"142":{"id":142,"normalDropId":5004,"monCapaticy":50.3986,"bronRule":[[[308,60,605,30,318,30,606,5],2]],"attackExp":[10,10],"eventID":[]},"143":{"id":143,"normalDropId":5004,"monCapaticy":51.9106,"bronRule":[[[305,60,311,30,624,10,318,10,330,1],2]],"attackExp":[10,10],"eventID":[]},"144":{"id":144,"normalDropId":5004,"monCapaticy":53.4679,"bronRule":[[[326,30,309,30,601,10,602,10,604,1],2]],"attackExp":[10,10],"eventID":[]},"145":{"id":145,"normalDropId":5004,"monCapaticy":55.0719,"bronRule":[[[344,1],1,1]],"attackExp":[10,10],"eventID":[]},"146":{"id":146,"normalDropId":5004,"monCapaticy":56.7241,"bronRule":[[[313,30,314,30,318,5,311,10,329,5,607,5],3]],"attackExp":[10,10],"eventID":[]},"147":{"id":147,"normalDropId":5004,"monCapaticy":58.4258,"bronRule":[[[314,30,315,30,318,5,601,5,328,10,325,10],3]],"attackExp":[10,10],"eventID":[]},"148":{"id":148,"normalDropId":5004,"monCapaticy":60.1786,"bronRule":[[[315,30,309,30,318,5,606,5,324,10,327,5],3]],"attackExp":[10,10],"eventID":[]},"149":{"id":149,"normalDropId":5004,"monCapaticy":61.984,"bronRule":[[[309,30,308,30,318,5,606,10,328,10,604,1],3]],"attackExp":[10,10],"eventID":[]},"150":{"id":150,"normalDropId":5005,"monCapaticy":63.8435,"bronRule":[[[345,1],1,1]],"attackExp":[10,10],"eventID":[]},"151":{"id":151,"normalDropId":5005,"monCapaticy":40,"bronRule":[[[303,10,301,10,318,3,329,3],3]],"attackExp":[100,100],"eventID":[]},"152":{"id":152,"normalDropId":5005,"monCapaticy":41.2,"bronRule":[[[301,10,317,10,318,5,328,2,311,1],3]],"attackExp":[50,50],"eventID":[]},"153":{"id":153,"normalDropId":5005,"monCapaticy":42.436,"bronRule":[[[317,20,305,5,318,5,607,1,324,1,325,3],3]],"attackExp":[50,50],"eventID":[]},"154":{"id":154,"normalDropId":5005,"monCapaticy":43.7091,"bronRule":[[[305,20,313,10,327,5,606,1,604,1],3]],"attackExp":[50,50],"eventID":[]},"155":{"id":155,"normalDropId":5005,"monCapaticy":45.0204,"bronRule":[[[335,1],1,1]],"attackExp":[50,50],"eventID":[]},"156":{"id":156,"normalDropId":5005,"monCapaticy":46.371,"bronRule":[[[313,30,314,10,318,5,311,5,329,5,607,2],3]],"attackExp":[20,20],"eventID":[]},"157":{"id":157,"normalDropId":5005,"monCapaticy":47.7621,"bronRule":[[[314,30,315,5,318,5,601,2,328,10,325,10],3]],"attackExp":[20,20],"eventID":[]},"158":{"id":158,"normalDropId":5005,"monCapaticy":49.195,"bronRule":[[[315,30,309,10,318,5,606,2,324,5,327,5],3]],"attackExp":[20,20],"eventID":[]},"159":{"id":159,"normalDropId":5005,"monCapaticy":50.6709,"bronRule":[[[309,20,308,30,318,10,606,2,328,10,604,1],3]],"attackExp":[20,20],"eventID":[]},"160":{"id":160,"normalDropId":5005,"monCapaticy":52.191,"bronRule":[[[339,1],1,1]],"attackExp":[20,20],"eventID":[]},"161":{"id":161,"normalDropId":5005,"monCapaticy":53.7567,"bronRule":[[[319,30,318,10,325,30,624,2,324,10,302,1],2]],"attackExp":[20,20],"eventID":[]},"162":{"id":162,"normalDropId":5005,"monCapaticy":55.3694,"bronRule":[[[308,30,605,30,318,30,606,2,602,2],2]],"attackExp":[20,20],"eventID":[]},"163":{"id":163,"normalDropId":5005,"monCapaticy":57.0305,"bronRule":[[[305,40,311,10,624,2,318,10,330,1],2]],"attackExp":[20,20],"eventID":[]},"164":{"id":164,"normalDropId":5005,"monCapaticy":58.7414,"bronRule":[[[326,30,319,30,601,5,602,5,604,1],2]],"attackExp":[20,20],"eventID":[]},"165":{"id":165,"normalDropId":5005,"monCapaticy":60.5036,"bronRule":[[[340,1],1,1]],"attackExp":[20,20],"eventID":[]},"166":{"id":166,"normalDropId":5005,"monCapaticy":62.3187,"bronRule":[[[309,30,318,5,311,5],3]],"attackExp":[20,20],"eventID":[]},"167":{"id":167,"normalDropId":5005,"monCapaticy":64.1883,"bronRule":[[[308,30,605,30,318,10,602,2],3]],"attackExp":[20,20],"eventID":[]},"168":{"id":168,"normalDropId":5005,"monCapaticy":66.1139,"bronRule":[[[309,20,324,6,611,4,302,1],3]],"attackExp":[20,20],"eventID":[]},"169":{"id":169,"normalDropId":5005,"monCapaticy":68.0973,"bronRule":[[[231,40,325,10,611,6,312,2,604,1],3]],"attackExp":[20,20],"eventID":[]},"170":{"id":170,"normalDropId":5005,"monCapaticy":70.1402,"bronRule":[[[341,1],1,1]],"attackExp":[20,20],"eventID":[]},"171":{"id":171,"normalDropId":5005,"monCapaticy":72.2444,"bronRule":[[[316,30,308,30,318,10,328,10,326,10],3]],"attackExp":[20,20],"eventID":[]},"172":{"id":172,"normalDropId":5005,"monCapaticy":74.4117,"bronRule":[[[308,30,319,30,318,10,325,15,607,5],3]],"attackExp":[20,20],"eventID":[]},"173":{"id":173,"normalDropId":5005,"monCapaticy":76.6441,"bronRule":[[[319,30,320,30,624,5,324,5,602,5,329,5],3]],"attackExp":[20,20],"eventID":[]},"174":{"id":174,"normalDropId":5005,"monCapaticy":78.9434,"bronRule":[[[320,30,303,30,311,10,611,5,624,5,327,5,604,1],3]],"attackExp":[20,20],"eventID":[]},"175":{"id":175,"normalDropId":5005,"monCapaticy":81.3117,"bronRule":[[[342,1],1,1]],"attackExp":[20,20],"eventID":[]},"176":{"id":176,"normalDropId":5005,"monCapaticy":83.7511,"bronRule":[[[303,30,301,30,318,10,328,10,606,5],3]],"attackExp":[20,20],"eventID":[]},"177":{"id":177,"normalDropId":5005,"monCapaticy":86.2636,"bronRule":[[[301,30,317,30,318,5,601,5,329,5,607,5],3]],"attackExp":[20,20],"eventID":[]},"178":{"id":178,"normalDropId":5005,"monCapaticy":88.8515,"bronRule":[[[317,30,305,30,318,5,607,5,624,5,325,10],3]],"attackExp":[20,20],"eventID":[]},"179":{"id":179,"normalDropId":5005,"monCapaticy":91.517,"bronRule":[[[305,30,313,30,327,5,602,5,606,5,604,1],3]],"attackExp":[20,20],"eventID":[]},"180":{"id":180,"normalDropId":5005,"monCapaticy":94.2625,"bronRule":[[[343,1],1,1]],"attackExp":[20,20],"eventID":[]},"181":{"id":181,"normalDropId":5005,"monCapaticy":97.0904,"bronRule":[[[305,40,611,4,235,40],3]],"attackExp":[20,20],"eventID":[]},"182":{"id":182,"normalDropId":5005,"monCapaticy":100.0031,"bronRule":[[[201,40,328,12,611,4,330,1],3]],"attackExp":[20,20],"eventID":[]},"183":{"id":183,"normalDropId":5005,"monCapaticy":103.0032,"bronRule":[[[309,20,324,6,611,4,302,1],3]],"attackExp":[20,20],"eventID":[]},"184":{"id":184,"normalDropId":5005,"monCapaticy":106.0933,"bronRule":[[[231,40,325,10,611,6,312,2,604,1],3]],"attackExp":[20,20],"eventID":[]},"185":{"id":185,"normalDropId":5005,"monCapaticy":109.2761,"bronRule":[[[333,1],1,1]],"attackExp":[20,20],"eventID":[]},"186":{"id":186,"normalDropId":5005,"monCapaticy":112.5544,"bronRule":[[[316,30,308,30,318,10,328,10,326,10],3]],"attackExp":[20,20],"eventID":[]},"187":{"id":187,"normalDropId":5005,"monCapaticy":115.931,"bronRule":[[[308,30,319,30,318,10,325,15,607,5],3]],"attackExp":[20,20],"eventID":[]},"188":{"id":188,"normalDropId":5005,"monCapaticy":119.4089,"bronRule":[[[319,60,624,2,324,10,602,5,329,5],3]],"attackExp":[20,20],"eventID":[]},"189":{"id":189,"normalDropId":5005,"monCapaticy":122.9912,"bronRule":[[[320,30,303,30,311,10,611,5,624,5,327,5,604,1],3]],"attackExp":[20,20],"eventID":[]},"190":{"id":190,"normalDropId":5005,"monCapaticy":126.6809,"bronRule":[[[334,1],1,1]],"attackExp":[20,20],"eventID":[]},"191":{"id":191,"normalDropId":5005,"monCapaticy":130.4813,"bronRule":[[[316,30,319,30,318,5,325,30,624,10,324,10,302,1],2]],"attackExp":[10,10],"eventID":[]},"192":{"id":192,"normalDropId":5005,"monCapaticy":134.3957,"bronRule":[[[308,60,605,30,318,30,606,5],2]],"attackExp":[10,10],"eventID":[]},"193":{"id":193,"normalDropId":5005,"monCapaticy":138.4276,"bronRule":[[[305,60,311,30,624,10,318,10,330,1],2]],"attackExp":[10,10],"eventID":[]},"194":{"id":194,"normalDropId":5005,"monCapaticy":142.5804,"bronRule":[[[326,30,309,30,601,10,602,10,604,1],2]],"attackExp":[10,10],"eventID":[]},"195":{"id":195,"normalDropId":5005,"monCapaticy":146.8578,"bronRule":[[[344,1],1,1]],"attackExp":[10,10],"eventID":[]},"196":{"id":196,"normalDropId":5005,"monCapaticy":151.2635,"bronRule":[[[313,30,314,30,318,5,311,10,329,5,607,5],3]],"attackExp":[10,10],"eventID":[]},"197":{"id":197,"normalDropId":5005,"monCapaticy":155.8014,"bronRule":[[[314,30,315,30,318,5,601,5,328,10,325,10],3]],"attackExp":[10,10],"eventID":[]},"198":{"id":198,"normalDropId":5005,"monCapaticy":160.4754,"bronRule":[[[315,30,309,30,318,5,606,5,324,10,327,5],3]],"attackExp":[10,10],"eventID":[]},"199":{"id":199,"normalDropId":5005,"monCapaticy":165.2897,"bronRule":[[[309,30,308,30,318,5,606,10,328,10,604,1],3]],"attackExp":[10,10],"eventID":[]},"200":{"id":200,"normalDropId":5006,"monCapaticy":170.2484,"bronRule":[[[345,1],1,1]],"attackExp":[10,10],"eventID":[]},"201":{"id":201,"normalDropId":5006,"monCapaticy":100,"bronRule":[[[303,10,301,10,318,3,329,3],3]],"attackExp":[100,100],"eventID":[]},"202":{"id":202,"normalDropId":5006,"monCapaticy":103,"bronRule":[[[301,10,317,10,318,5,328,2,311,1],3]],"attackExp":[50,50],"eventID":[]},"203":{"id":203,"normalDropId":5006,"monCapaticy":106.09,"bronRule":[[[317,20,305,5,318,5,607,1,324,1,325,3],3]],"attackExp":[50,50],"eventID":[]},"204":{"id":204,"normalDropId":5006,"monCapaticy":109.2727,"bronRule":[[[305,20,313,10,327,5,606,1,604,1],3]],"attackExp":[50,50],"eventID":[]},"205":{"id":205,"normalDropId":5006,"monCapaticy":112.5509,"bronRule":[[[335,1],1,1]],"attackExp":[50,50],"eventID":[]},"206":{"id":206,"normalDropId":5006,"monCapaticy":115.9274,"bronRule":[[[313,30,314,10,318,5,311,5,329,5,607,2],3]],"attackExp":[20,20],"eventID":[]},"207":{"id":207,"normalDropId":5006,"monCapaticy":119.4052,"bronRule":[[[314,30,315,5,318,5,601,2,328,10,325,10],3]],"attackExp":[20,20],"eventID":[]},"208":{"id":208,"normalDropId":5006,"monCapaticy":122.9874,"bronRule":[[[315,30,309,10,318,5,606,2,324,5,327,5],3]],"attackExp":[20,20],"eventID":[]},"209":{"id":209,"normalDropId":5006,"monCapaticy":126.677,"bronRule":[[[309,20,308,30,318,10,606,2,328,10,604,1],3]],"attackExp":[20,20],"eventID":[]},"210":{"id":210,"normalDropId":5006,"monCapaticy":130.4773,"bronRule":[[[339,1],1,1]],"attackExp":[20,20],"eventID":[]},"211":{"id":211,"normalDropId":5006,"monCapaticy":134.3916,"bronRule":[[[319,30,318,10,325,30,624,2,324,10,302,1],2]],"attackExp":[20,20],"eventID":[]},"212":{"id":212,"normalDropId":5006,"monCapaticy":138.4233,"bronRule":[[[308,30,605,30,318,30,606,2,602,2],2]],"attackExp":[20,20],"eventID":[]},"213":{"id":213,"normalDropId":5006,"monCapaticy":142.576,"bronRule":[[[305,40,311,10,624,2,318,10,330,1],2]],"attackExp":[20,20],"eventID":[]},"214":{"id":214,"normalDropId":5006,"monCapaticy":146.8533,"bronRule":[[[326,30,319,30,601,5,602,5,604,1],2]],"attackExp":[20,20],"eventID":[]},"215":{"id":215,"normalDropId":5006,"monCapaticy":151.2589,"bronRule":[[[340,1],1,1]],"attackExp":[20,20],"eventID":[]},"216":{"id":216,"normalDropId":5006,"monCapaticy":155.7967,"bronRule":[[[309,30,318,5,311,5],3]],"attackExp":[20,20],"eventID":[]},"217":{"id":217,"normalDropId":5006,"monCapaticy":160.4706,"bronRule":[[[308,30,605,30,318,10,602,2],3]],"attackExp":[20,20],"eventID":[]},"218":{"id":218,"normalDropId":5006,"monCapaticy":165.2847,"bronRule":[[[309,20,324,6,611,4,302,1],3]],"attackExp":[20,20],"eventID":[]},"219":{"id":219,"normalDropId":5006,"monCapaticy":170.2432,"bronRule":[[[231,40,325,10,611,6,312,2,604,1],3]],"attackExp":[20,20],"eventID":[]},"220":{"id":220,"normalDropId":5006,"monCapaticy":175.3505,"bronRule":[[[341,1],1,1]],"attackExp":[20,20],"eventID":[]},"221":{"id":221,"normalDropId":5006,"monCapaticy":180.611,"bronRule":[[[316,30,308,30,318,10,328,10,326,10],3]],"attackExp":[20,20],"eventID":[]},"222":{"id":222,"normalDropId":5006,"monCapaticy":186.0293,"bronRule":[[[308,30,319,30,318,10,325,15,607,5],3]],"attackExp":[20,20],"eventID":[]},"223":{"id":223,"normalDropId":5006,"monCapaticy":191.6102,"bronRule":[[[319,30,320,30,624,5,324,5,602,5,329,5],3]],"attackExp":[20,20],"eventID":[]},"224":{"id":224,"normalDropId":5006,"monCapaticy":197.3585,"bronRule":[[[320,30,303,30,311,10,611,5,624,5,327,5,604,1],3]],"attackExp":[20,20],"eventID":[]},"225":{"id":225,"normalDropId":5006,"monCapaticy":203.2793,"bronRule":[[[342,1],1,1]],"attackExp":[20,20],"eventID":[]},"226":{"id":226,"normalDropId":5006,"monCapaticy":209.3777,"bronRule":[[[303,30,301,30,318,10,328,10,606,5],3]],"attackExp":[20,20],"eventID":[]},"227":{"id":227,"normalDropId":5006,"monCapaticy":215.659,"bronRule":[[[301,30,317,30,318,5,601,5,329,5,607,5],3]],"attackExp":[20,20],"eventID":[]},"228":{"id":228,"normalDropId":5006,"monCapaticy":222.1288,"bronRule":[[[317,30,305,30,318,5,607,5,624,5,325,10],3]],"attackExp":[20,20],"eventID":[]},"229":{"id":229,"normalDropId":5006,"monCapaticy":228.7927,"bronRule":[[[305,30,313,30,327,5,602,5,606,5,604,1],3]],"attackExp":[20,20],"eventID":[]},"230":{"id":230,"normalDropId":5006,"monCapaticy":235.6565,"bronRule":[[[343,1],1,1]],"attackExp":[20,20],"eventID":[]},"231":{"id":231,"normalDropId":5006,"monCapaticy":242.7262,"bronRule":[[[305,40,611,4,235,40],3]],"attackExp":[20,20],"eventID":[]},"232":{"id":232,"normalDropId":5006,"monCapaticy":250.008,"bronRule":[[[201,40,328,12,611,4,330,1],3]],"attackExp":[20,20],"eventID":[]},"233":{"id":233,"normalDropId":5006,"monCapaticy":257.5082,"bronRule":[[[309,20,324,6,611,4,302,1],3]],"attackExp":[20,20],"eventID":[]},"234":{"id":234,"normalDropId":5006,"monCapaticy":265.2334,"bronRule":[[[231,40,325,10,611,6,312,2,604,1],3]],"attackExp":[20,20],"eventID":[]},"235":{"id":235,"normalDropId":5006,"monCapaticy":273.1904,"bronRule":[[[333,1],1,1]],"attackExp":[20,20],"eventID":[]},"236":{"id":236,"normalDropId":5006,"monCapaticy":281.3861,"bronRule":[[[316,30,308,30,318,10,328,10,326,10],3]],"attackExp":[20,20],"eventID":[]},"237":{"id":237,"normalDropId":5006,"monCapaticy":289.8277,"bronRule":[[[308,30,319,30,318,10,325,15,607,5],3]],"attackExp":[20,20],"eventID":[]},"238":{"id":238,"normalDropId":5006,"monCapaticy":298.5225,"bronRule":[[[319,60,624,2,324,10,602,5,329,5],3]],"attackExp":[20,20],"eventID":[]},"239":{"id":239,"normalDropId":5006,"monCapaticy":307.4782,"bronRule":[[[320,30,303,30,311,10,611,5,624,5,327,5,604,1],3]],"attackExp":[20,20],"eventID":[]},"240":{"id":240,"normalDropId":5006,"monCapaticy":316.7025,"bronRule":[[[334,1],1,1]],"attackExp":[20,20],"eventID":[]},"241":{"id":241,"normalDropId":5006,"monCapaticy":326.2036,"bronRule":[[[316,30,319,30,318,5,325,30,624,10,324,10,302,1],2]],"attackExp":[10,10],"eventID":[]},"242":{"id":242,"normalDropId":5006,"monCapaticy":335.9897,"bronRule":[[[308,60,605,30,318,30,606,5],2]],"attackExp":[10,10],"eventID":[]},"243":{"id":243,"normalDropId":5006,"monCapaticy":346.0694,"bronRule":[[[305,60,311,30,624,10,318,10,330,1],2]],"attackExp":[10,10],"eventID":[]},"244":{"id":244,"normalDropId":5006,"monCapaticy":356.4515,"bronRule":[[[326,30,309,30,601,10,602,10,604,1],2]],"attackExp":[10,10],"eventID":[]},"245":{"id":245,"normalDropId":5006,"monCapaticy":367.145,"bronRule":[[[344,1],1,1]],"attackExp":[10,10],"eventID":[]},"246":{"id":246,"normalDropId":5006,"monCapaticy":378.1594,"bronRule":[[[313,30,314,30,318,5,311,10,329,5,607,5],3]],"attackExp":[10,10],"eventID":[]},"247":{"id":247,"normalDropId":5006,"monCapaticy":389.5042,"bronRule":[[[314,30,315,30,318,5,601,5,328,10,325,10],3]],"attackExp":[10,10],"eventID":[]},"248":{"id":248,"normalDropId":5006,"monCapaticy":401.1893,"bronRule":[[[315,30,309,30,318,5,606,5,324,10,327,5],3]],"attackExp":[10,10],"eventID":[]},"249":{"id":249,"normalDropId":5006,"monCapaticy":413.225,"bronRule":[[[309,30,308,30,318,5,606,10,328,10,604,1],3]],"attackExp":[10,10],"eventID":[]},"250":{"id":250,"normalDropId":5006,"monCapaticy":320,"bronRule":[[[345,1],1,1]],"attackExp":[10,10],"eventID":[]},"251":{"id":251,"normalDropId":5006,"monCapaticy":329.6,"bronRule":[[[303,10,301,10,318,3,329,3],3]],"attackExp":[100,100],"eventID":[]},"252":{"id":252,"normalDropId":5006,"monCapaticy":339.488,"bronRule":[[[301,10,317,10,318,5,328,2,311,1],3]],"attackExp":[50,50],"eventID":[]},"253":{"id":253,"normalDropId":5006,"monCapaticy":349.6726,"bronRule":[[[317,20,305,5,318,5,607,1,324,1,325,3],3]],"attackExp":[50,50],"eventID":[]},"254":{"id":254,"normalDropId":5006,"monCapaticy":360.1628,"bronRule":[[[305,20,313,10,327,5,606,1,604,1],3]],"attackExp":[50,50],"eventID":[]},"255":{"id":255,"normalDropId":5006,"monCapaticy":370.9677,"bronRule":[[[335,1],1,1]],"attackExp":[50,50],"eventID":[]},"256":{"id":256,"normalDropId":5006,"monCapaticy":382.0967,"bronRule":[[[313,30,314,10,318,5,311,5,329,5,607,2],3]],"attackExp":[50,50],"eventID":[]},"257":{"id":257,"normalDropId":5006,"monCapaticy":393.5596,"bronRule":[[[314,30,315,5,318,5,601,2,328,10,325,10],3]],"attackExp":[50,50],"eventID":[]},"258":{"id":258,"normalDropId":5006,"monCapaticy":405.3664,"bronRule":[[[315,30,309,10,318,5,606,2,324,5,327,5],3]],"attackExp":[34,34],"eventID":[]},"259":{"id":259,"normalDropId":5006,"monCapaticy":417.5274,"bronRule":[[[309,20,308,30,318,10,606,2,328,10,604,1],3]],"attackExp":[34,34],"eventID":[]},"260":{"id":260,"normalDropId":5006,"monCapaticy":430.0532,"bronRule":[[[339,1],1,1]],"attackExp":[34,34],"eventID":[]},"261":{"id":261,"normalDropId":5006,"monCapaticy":442.9548,"bronRule":[[[319,30,318,10,325,30,624,2,324,10,302,1],2]],"attackExp":[50,50],"eventID":[]},"262":{"id":262,"normalDropId":5006,"monCapaticy":456.2434,"bronRule":[[[308,30,605,30,318,30,606,2,602,2],2]],"attackExp":[50,50],"eventID":[]},"263":{"id":263,"normalDropId":5006,"monCapaticy":469.9307,"bronRule":[[[305,40,311,10,624,2,318,10,330,1],2]],"attackExp":[34,34],"eventID":[]},"264":{"id":264,"normalDropId":5006,"monCapaticy":484.0286,"bronRule":[[[326,30,319,30,601,5,602,5,604,1],2]],"attackExp":[34,34],"eventID":[]},"265":{"id":265,"normalDropId":5006,"monCapaticy":498.5495,"bronRule":[[[340,1],1,1]],"attackExp":[34,34],"eventID":[]},"266":{"id":266,"normalDropId":5006,"monCapaticy":513.506,"bronRule":[[[309,30,318,5,311,5],3]],"attackExp":[50,50],"eventID":[]},"267":{"id":267,"normalDropId":5006,"monCapaticy":528.9112,"bronRule":[[[308,30,605,30,318,10,602,2],3]],"attackExp":[50,50],"eventID":[]},"268":{"id":268,"normalDropId":5006,"monCapaticy":544.7785,"bronRule":[[[309,20,324,6,611,4,302,1],3]],"attackExp":[34,34],"eventID":[]},"269":{"id":269,"normalDropId":5006,"monCapaticy":561.1219,"bronRule":[[[231,40,325,10,611,6,312,2,604,1],3]],"attackExp":[34,34],"eventID":[]},"270":{"id":270,"normalDropId":5006,"monCapaticy":577.9556,"bronRule":[[[341,1],1,1]],"attackExp":[34,34],"eventID":[]},"271":{"id":271,"normalDropId":5006,"monCapaticy":595.2943,"bronRule":[[[316,30,308,30,318,10,328,10,326,10],3]],"attackExp":[50,50],"eventID":[]},"272":{"id":272,"normalDropId":5006,"monCapaticy":613.1531,"bronRule":[[[308,30,319,30,318,10,325,15,607,5],3]],"attackExp":[50,50],"eventID":[]},"273":{"id":273,"normalDropId":5006,"monCapaticy":631.5477,"bronRule":[[[319,30,320,30,624,5,324,5,602,5,329,5],3]],"attackExp":[34,34],"eventID":[]},"274":{"id":274,"normalDropId":5006,"monCapaticy":650.4941,"bronRule":[[[320,30,303,30,311,10,611,5,624,5,327,5,604,1],3]],"attackExp":[34,34],"eventID":[]},"275":{"id":275,"normalDropId":5006,"monCapaticy":670.0089,"bronRule":[[[342,1],1,1]],"attackExp":[34,34],"eventID":[]},"276":{"id":276,"normalDropId":5006,"monCapaticy":690.1092,"bronRule":[[[303,30,301,30,318,10,328,10,606,5],3]],"attackExp":[50,50],"eventID":[]},"277":{"id":277,"normalDropId":5006,"monCapaticy":710.8125,"bronRule":[[[301,30,317,30,318,5,601,5,329,5,607,5],3]],"attackExp":[50,50],"eventID":[]},"278":{"id":278,"normalDropId":5006,"monCapaticy":732.1369,"bronRule":[[[317,30,305,30,318,5,607,5,624,5,325,10],3]],"attackExp":[34,34],"eventID":[]},"279":{"id":279,"normalDropId":5006,"monCapaticy":754.101,"bronRule":[[[305,30,313,30,327,5,602,5,606,5,604,1],3]],"attackExp":[34,34],"eventID":[]},"280":{"id":280,"normalDropId":5006,"monCapaticy":776.724,"bronRule":[[[343,1],1,1]],"attackExp":[34,34],"eventID":[]},"281":{"id":281,"normalDropId":5006,"monCapaticy":800.0257,"bronRule":[[[305,40,611,4,235,40],3]],"attackExp":[50,50],"eventID":[]},"282":{"id":282,"normalDropId":5006,"monCapaticy":824.0265,"bronRule":[[[201,40,328,12,611,4,330,1],3]],"attackExp":[50,50],"eventID":[]},"283":{"id":283,"normalDropId":5006,"monCapaticy":848.7473,"bronRule":[[[309,20,324,6,611,4,302,1],3]],"attackExp":[34,34],"eventID":[]},"284":{"id":284,"normalDropId":5006,"monCapaticy":874.2097,"bronRule":[[[231,40,325,10,611,6,312,2,604,1],3]],"attackExp":[34,34],"eventID":[]},"285":{"id":285,"normalDropId":5006,"monCapaticy":900.436,"bronRule":[[[333,1],1,1]],"attackExp":[34,34],"eventID":[]},"286":{"id":286,"normalDropId":5006,"monCapaticy":927.4491,"bronRule":[[[316,30,308,30,318,10,328,10,326,10],3]],"attackExp":[50,50],"eventID":[]},"287":{"id":287,"normalDropId":5006,"monCapaticy":955.2726,"bronRule":[[[308,30,319,30,318,10,325,15,607,5],3]],"attackExp":[50,50],"eventID":[]},"288":{"id":288,"normalDropId":5006,"monCapaticy":983.9308,"bronRule":[[[319,60,624,2,324,10,602,5,329,5],3]],"attackExp":[34,34],"eventID":[]},"289":{"id":289,"normalDropId":5006,"monCapaticy":1013.4487,"bronRule":[[[320,30,303,30,311,10,611,5,624,5,327,5,604,1],3]],"attackExp":[34,34],"eventID":[]},"290":{"id":290,"normalDropId":5006,"monCapaticy":1043.8522,"bronRule":[[[334,1],1,1]],"attackExp":[34,34],"eventID":[]},"291":{"id":291,"normalDropId":5006,"monCapaticy":1075.1678,"bronRule":[[[316,30,319,30,318,5,325,30,624,10,324,10,302,1],2]],"attackExp":[50,50],"eventID":[]},"292":{"id":292,"normalDropId":5006,"monCapaticy":1107.4228,"bronRule":[[[308,60,605,30,318,30,606,5],2]],"attackExp":[50,50],"eventID":[]},"293":{"id":293,"normalDropId":5006,"monCapaticy":1140.6455,"bronRule":[[[305,60,311,30,624,10,318,10,330,1],2]],"attackExp":[34,34],"eventID":[]},"294":{"id":294,"normalDropId":5006,"monCapaticy":1174.8649,"bronRule":[[[326,30,309,30,601,10,602,10,604,1],2]],"attackExp":[34,34],"eventID":[]},"295":{"id":295,"normalDropId":5006,"monCapaticy":1210.1108,"bronRule":[[[344,1],1,1]],"attackExp":[34,34],"eventID":[]},"296":{"id":296,"normalDropId":5006,"monCapaticy":1246.4141,"bronRule":[[[313,30,314,30,318,5,311,10,329,5,607,5],3]],"attackExp":[10,10],"eventID":[]},"297":{"id":297,"normalDropId":5006,"monCapaticy":1283.8065,"bronRule":[[[314,30,315,30,318,5,601,5,328,10,325,10],3]],"attackExp":[10,10],"eventID":[]},"298":{"id":298,"normalDropId":5006,"monCapaticy":1322.3207,"bronRule":[[[315,30,309,30,318,5,606,5,324,10,327,5],3]],"attackExp":[10,10],"eventID":[]},"299":{"id":299,"normalDropId":5006,"monCapaticy":1361.9903,"bronRule":[[[309,30,308,30,318,5,606,10,328,10,604,1],3]],"attackExp":[10,10],"eventID":[]},"300":{"id":300,"normalDropId":5006,"monCapaticy":1402.85,"bronRule":[[[345,1],1,1]],"attackExp":[10,10],"eventID":[]}}]],0,0,[],[],[]]